Workbook

Sheet Property Management Overview
D1: PROPERTY MANAGEMENT SPREADSHEET | I1: 2026
B2: MULTI-PROPERTY OVERVIEW | C2: Enter data on individual property sheets. Overview information will populate automatically.
B3: INCOME | C3: YALE 2516 | D3: YALE 0111 | E3: YALE 0727 | F3: YALE 0728 | G3: Amega Crown A8-10 | H3: 6 | I3: 7 | J3: 8 | K3: 9 | L3: 10 | M3: 11 | N3: 12 | O3: YTD TOTAL
B4: MULTI-PROPERTY INCOME OVERVIEW
B5: RENTAL INCOME | C5: ='YALE 2516'!O5 -> 0 | D5: ='YALE 0111'!O5 -> 12510000 | E5: ='YALE 0727'!O5 -> 5000000 | F5: ='YALE 0728'!O5 -> 0 | G5: ='Amega Crown A8-10'!O5 -> 2000000 | H5: ='Property 6'!O5 -> 0 | I5: ='Property 7'!O5 -> 0 | J5: ='Property 8'!O5 -> 0 | K5: ='Property 9'!O5 -> 0 | L5: ='Property 10'!O5 -> 0 | M5: ='Property 11'!O5 -> 0 | N5: ='Property 12'!O5 -> 0 | O5: =SUM(C5:N5) -> 19510000
B6: OTHER RENTAL INCOME – Late Fees, Etc. | C6: ='YALE 2516'!O6 -> 0 | D6: ='YALE 0111'!O6 -> 0 | E6: ='YALE 0727'!O6 -> 0 | F6: ='YALE 0728'!O6 -> 0 | G6: ='Amega Crown A8-10'!O6 -> 0 | H6: ='Property 6'!O6 -> 0 | I6: ='Property 7'!O6 -> 0 | J6: ='Property 8'!O6 -> 0 | K6: ='Property 9'!O6 -> 0 | L6: ='Property 10'!O6 -> 0 | M6: ='Property 11'!O6 -> 0 | N6: ='Property 12'!O6 -> 0 | O6: =SUM(C6:N6) -> 0
B7: GROSS RENTAL INCOME | C7: =SUM(C5:C6) -> 0 | D7: =SUM(D5:D6) -> 12510000 | E7: =SUM(E5:E6) -> 5000000 | F7: =SUM(F5:F6) -> 0 | G7: =SUM(G5:G6) -> 2000000 | H7: =SUM(H5:H6) -> 0 | I7: =SUM(I5:I6) -> 0 | J7: =SUM(J5:J6) -> 0 | ... N7: =SUM(N5:N6) -> 0 | O7: =SUM(C7:N7) -> 19510000
B9: EXPENSES | C9: 1 | D9: 2 | E9: 3 | F9: 4 | G9: 5 | H9: 6 | I9: 7 | J9: 8 | K9: 9 | L9: 10 | M9: 11 | N9: 12 | O9: YTD TOTAL
B10: MULTI-PROPERTY EXPENSES OVERVIEW
B11: MARKETING / ADVERTISING | C11: ='YALE 2516'!O11 -> 0 | D11: ='YALE 0111'!O11 -> 0 | E11: ='YALE 0727'!O11 -> 0 | F11: ='YALE 0728'!O11 -> 0 | G11: ='Amega Crown A8-10'!O11 -> 0 | H11: ='Property 6'!O11 -> 0 | I11: ='Property 7'!O11 -> 0 | J11: ='Property 8'!O11 -> 0 | K11: ='Property 9'!O11 -> 0 | L11: ='Property 10'!O11 -> 0 | M11: ='Property 11'!O11 -> 0 | N11: ='Property 12'!O11 -> 0 | O11: =SUM(C11:N11) -> 0
B12: SERVICE CHARGE | C12: ='YALE 2516'!O12 -> 0 | D12: ='YALE 0111'!O12 -> 0 | E12: ='YALE 0727'!O12 -> 900000 | F12: ='YALE 0728'!O12 -> 0 | G12: ='Amega Crown A8-10'!O12 -> 0 | H12: ='Property 6'!O12 -> 0 | I12: ='Property 7'!O12 -> 0 | J12: ='Property 8'!O12 -> 0 | K12: ='Property 9'!O12 -> 0 | L12: ='Property 10'!O12 -> 0 | M12: ='Property 11'!O12 -> 0 | N12: ='Property 12'!O12 -> 0 | O12: =SUM(C12:N12) -> 900000
B13: AGENT FEES / COMMISSIONS | C13: ='YALE 2516'!O13 -> 0 | D13: ='YALE 0111'!O13 -> 1260000 | E13: ='YALE 0727'!O13 -> 0 | F13: ='YALE 0728'!O13 -> 0 | G13: ='Amega Crown A8-10'!O13 -> 200000 | H13: ='Property 6'!O13 -> 0 | I13: ='Property 7'!O13 -> 0 | J13: ='Property 8'!O13 -> 0 | K13: ='Property 9'!O13 -> 0 | L13: ='Property 10'!O13 -> 0 | M13: ='Property 11'!O13 -> 0 | N13: ='Property 12'!O13 -> 0 | O13: =SUM(C13:N13) -> 1460000
B14: AIR+LISTRIK | C14: ='YALE 2516'!O14 -> 0 | D14: ='YALE 0111'!O14 -> 0 | E14: ='YALE 0727'!O14 -> 0 | F14: ='YALE 0728'!O14 -> 0 | G14: ='Amega Crown A8-10'!O14 -> 0 | H14: ='Property 6'!O14 -> 0 | I14: ='Property 7'!O14 -> 0 | J14: ='Property 8'!O14 -> 0 | K14: ='Property 9'!O14 -> 0 | L14: ='Property 10'!O14 -> 0 | M14: ='Property 11'!O14 -> 0 | N14: ='Property 12'!O14 -> 0 | O14: =SUM(C14:N14) -> 0
B15: INTERIOR MAINTENANCE | C15: ='YALE 2516'!O15 -> 0 | D15: ='YALE 0111'!O15 -> 0 | E15: ='YALE 0727'!O15 -> 0 | F15: ='YALE 0728'!O15 -> 0 | G15: ='Amega Crown A8-10'!O15 -> 0 | H15: ='Property 6'!O15 -> 0 | I15: ='Property 7'!O15 -> 0 | J15: ='Property 8'!O15 -> 0 | K15: ='Property 9'!O15 -> 0 | L15: ='Property 10'!O15 -> 0 | M15: ='Property 11'!O15 -> 0 | N15: ='Property 12'!O15 -> 0 | O15: =SUM(C15:N15) -> 0
B16: INTERIOR REPAIRS | C16: ='YALE 2516'!O16 -> 0 | D16: ='YALE 0111'!O16 -> 0 | E16: ='YALE 0727'!O16 -> 0 | F16: ='YALE 0728'!O16 -> 0 | G16: ='Amega Crown A8-10'!O16 -> 0 | H16: ='Property 6'!O16 -> 0 | I16: ='Property 7'!O16 -> 0 | J16: ='Property 8'!O16 -> 0 | K16: ='Property 9'!O16 -> 0 | L16: ='Property 10'!O16 -> 0 | M16: ='Property 11'!O16 -> 0 | N16: ='Property 12'!O16 -> 0 | O16: =SUM(C16:N16) -> 0
B17: HOUSEKEEPING | C17: ='YALE 2516'!O17 -> 0 | D17: ='YALE 0111'!O17 -> 0 | E17: ='YALE 0727'!O17 -> 0 | F17: ='YALE 0728'!O17 -> 0 | G17: ='Amega Crown A8-10'!O17 -> 0 | H17: ='Property 6'!O17 -> 0 | I17: ='Property 7'!O17 -> 0 | J17: ='Property 8'!O17 -> 0 | K17: ='Property 9'!O17 -> 0 | L17: ='Property 10'!O17 -> 0 | M17: ='Property 11'!O17 -> 0 | N17: ='Property 12'!O17 -> 0 | O17: =SUM(C17:N17) -> 0
B18: EXTERIOR MAINTENANCE | C18: ='YALE 2516'!O18 -> 0 | D18: ='YALE 0111'!O18 -> 0 | E18: ='YALE 0727'!O18 -> 0 | F18: ='YALE 0728'!O18 -> 0 | G18: ='Amega Crown A8-10'!O18 -> 0 | H18: ='Property 6'!O18 -> 0 | I18: ='Property 7'!O18 -> 0 | J18: ='Property 8'!O18 -> 0 | K18: ='Property 9'!O18 -> 0 | L18: ='Property 10'!O18 -> 0 | M18: ='Property 11'!O18 -> 0 | N18: ='Property 12'!O18 -> 0 | O18: =SUM(C18:N18) -> 0
B19: EXTERIOR REPAIRS | C19: ='YALE 2516'!O19 -> 0 | D19: ='YALE 0111'!O19 -> 0 | E19: ='YALE 0727'!O19 -> 0 | F19: ='YALE 0728'!O19 -> 0 | G19: ='Amega Crown A8-10'!O19 -> 0 | H19: ='Property 6'!O19 -> 0 | I19: ='Property 7'!O19 -> 0 | J19: ='Property 8'!O19 -> 0 | K19: ='Property 9'!O19 -> 0 | L19: ='Property 10'!O19 -> 0 | M19: ='Property 11'!O19 -> 0 | N19: ='Property 12'!O19 -> 0 | O19: =SUM(C19:N19) -> 0
B20: GROUNDSKEEPING | C20: ='YALE 2516'!O20 -> 0 | D20: ='YALE 0111'!O20 -> 0 | E20: ='YALE 0727'!O20 -> 0 | F20: ='YALE 0728'!O20 -> 0 | G20: ='Amega Crown A8-10'!O20 -> 0 | H20: ='Property 6'!O20 -> 0 | I20: ='Property 7'!O20 -> 0 | J20: ='Property 8'!O20 -> 0 | K20: ='Property 9'!O20 -> 0 | L20: ='Property 10'!O20 -> 0 | M20: ='Property 11'!O20 -> 0 | N20: ='Property 12'!O20 -> 0 | O20: =SUM(C20:N20) -> 0
B21: AIR +LISTRIK | C21: ='YALE 2516'!O21 -> 0 | D21: ='YALE 0111'!O21 -> 0 | E21: ='YALE 0727'!O21 -> 0 | F21: ='YALE 0728'!O21 -> 0 | G21: ='Amega Crown A8-10'!O21 -> 0 | H21: ='Property 6'!O21 -> 0 | I21: ='Property 7'!O21 -> 0 | J21: ='Property 8'!O21 -> 0 | K21: ='Property 9'!O21 -> 0 | L21: ='Property 10'!O21 -> 0 | M21: ='Property 11'!O21 -> 0 | N21: ='Property 12'!O21 -> 0 | O21: =SUM(C21:N21) -> 0
B22: GAS | C22: ='YALE 2516'!O22 -> 0 | D22: ='YALE 0111'!O22 -> 0 | E22: ='YALE 0727'!O22 -> 0 | F22: ='YALE 0728'!O22 -> 0 | G22: ='Amega Crown A8-10'!O22 -> 0 | H22: ='Property 6'!O22 -> 0 | I22: ='Property 7'!O22 -> 0 | J22: ='Property 8'!O22 -> 0 | K22: ='Property 9'!O22 -> 0 | L22: ='Property 10'!O22 -> 0 | M22: ='Property 11'!O22 -> 0 | N22: ='Property 12'!O22 -> 0 | O22: =SUM(C22:N22) -> 0
... B42: OTHER | C42: ='YALE 2516'!O42 -> 0 | D42: ='YALE 0111'!O42 -> 0 | E42: ='YALE 0727'!O42 -> 0 | F42: ='YALE 0728'!O42 -> 0 | G42: ='Amega Crown A8-10'!O42 -> 0 | H42: ='Property 6'!O42 -> 0 | I42: ='Property 7'!O42 -> 0 | J42: ='Property 8'!O42 -> 0 | K42: ='Property 9'!O42 -> 0 | L42: ='Property 10'!O42 -> 0 | M42: ='Property 11'!O42 -> 0 | N42: ='Property 12'!O42 -> 0 | O42: =SUM(C42:N42) -> 0
B43: TOTAL EXPENSES | C43: =SUM(C11:C42) -> 0 | D43: =SUM(D11:D42) -> 1500675 | E43: =SUM(E11:E42) -> 1450675 | F43: =SUM(F11:F42) -> 240675 | G43: =SUM(G11:G42) -> 388577 | H43: =SUM(H11:H42) -> 0 | I43: =SUM(I11:I42) -> 0 | J43: =SUM(J11:J42) -> 0 | ... N43: =SUM(N11:N42) -> 0 | O43: =SUM(C43:N43) -> 3580602
B45: YEAR-TO-DATE INCOME LESS EXPENSES | C45: =C7-C43 -> 0 | D45: =D7-D43 -> 11009325 | E45: =E7-E43 -> 3549325 | F45: =F7-F43 -> -240675 | G45: =G7-G43 -> 1611423 | H45: =H7-H43 -> 0 | I45: =I7-I43 -> 0 | J45: =J7-J43 -> 0 | ... O45: =O7-O43 -> 15929398
B47: CLICK HERE TO CREATE IN SMARTSHEET

Sheet Harga+Biaya Perolehan
A1: Unit | B1: Harga | C1: BPHTB | D1: AJB+Balik Nama+PNBP | F1: Appraisal | G1: Perbaikan | I1: Total | J1: DP | L1: Tanggal AJB | M1: Pinjaman | N1: Lender | O1: Equity | P1: Cicilan bulanan | Q1: Tenor | R1: Fee Bank (Asuransi+Admin+biaya notaris)
A2: Yale 2516 | B2: 230000000 | C2: 5425000 | D2: 4628000 | F2: 750000 | G2: 5000000 | I2: =SUM(B2:G2) -> 245803000 | J2: 50000000 | L2: 45147 | M2: 0 | N2: Stockbit+OCBC PREMIER | O2: =I2-M2 -> 245803000
A3: Yale 0111 | B3: 235889745 | D3: 21968182 | F3: 750000 | G3: 10000000 | I3: =SUM(B3:G3) -> 268607927 | J3: 35000000 | M3: 0 | N3: Mirae | O3: =I3-M3 -> 268607927
A4: Yale 0728 | B4: 250000000 | C4: 12725000 | F4: 550000 | G4: 2000000 | I4: =SUM(B4:G4) -> 265275000 | J4: Papa | N4: BCA | O4: =I4-M4 -> 265275000 | P4: - | Q4: 5
A5: Yale 0727 | B5: 250000000 | C5: 15350000 | F5: 550000 | G5: 2000000 | I5: =SUM(B5:G5) -> 267900000 | J5: Papa | N5: BCA | O5: =I5-M5 -> 267900000 | P5: - | Q5: 5
I6: =SUM(I2:I5) -> 1047585927 | M6: 990000000 | N6: BCA | R6: 10983570
A7: Amega | B7: 200000000 | G7: 7000000 | H7: AC SINK GORDEN

Sheet YALE 2516
B1: PROPERTY MANAGEMENT SPREADSHEET TEMPLATE
B2: YALE 10 | C2: 123 Main Street, City, State 10001
B3: INCOME | C3: JAN | D3: FEB | E3: MAR | F3: APR | G3: MAY | H3: JUN | I3: JUL | J3: AUG | K3: 0 | L3: OCT | M3: NOV | N3: DEC | O3: YR TOTAL
B4: MULTI-PROPERTY INCOME OVERVIEW | I4: 0 | K4: 0 | L4: 0 | M4: 0 | N4: 0
B5: ='Property Management Overview'!B5 -> RENTAL INCOME | C5: - | D5: - | E5: 0 | F5: 0 | G5: 0 | H5: 0 | I5: 0 | J5: 0 | K5: - | L5: - | M5: - | N5: - | O5: =SUM(C5:N5) -> 0
B6: ='Property Management Overview'!B6 -> OTHER RENTAL INCOME – Late Fees, Etc. | C6: 0 | D6: 0 | E6: 0 | F6: 0 | G6: 0 | H6: 0 | I6: 0 | J6: 0 | K6: 0 | L6: 0 | M6: 0 | N6: 0 | O6: =SUM(C6:N6) -> 0
B7: GROSS RENTAL INCOME | C7: =SUM(C5:C6) -> 0 | D7: =SUM(D5:D6) -> 0 | E7: =SUM(E5:E6) -> 0 | F7: =SUM(F5:F6) -> 0 | G7: =SUM(G5:G6) -> 0 | H7: =SUM(H5:H6) -> 0 | I7: 0 | J7: =SUM(J5:J6) -> 0 | K7: =SUM(K5:K6) -> 0 | L7: =SUM(L5:L6) -> 0 | M7: =SUM(M5:M6) -> 0 | N7: =SUM(N5:N6) -> 0 | O7: =SUM(C7:N7) -> 0
B9: EXPENSES | C9: JAN | D9: FEB | E9: MAR | F9: APR | G9: MAY | H9: JUN | I9: JUL | J9: AUG | K9: SEPT | L9: OCT | M9: NOV | N9: DEC | O9: YR TOTAL
B10: ='Property Management Overview'!B10 -> MULTI-PROPERTY EXPENSES OVERVIEW | I10: 0
B11: ='Property Management Overview'!B11 -> MARKETING / ADVERTISING | C11: 0 | D11: 0 | E11: 0 | F11: 0 | G11: 0 | H11: 0 | I11: 0 | J11: 0 | K11: 0 | L11: 0 | M11: 0 | N11: 0 | O11: =SUM(C11:N11) -> 0
B12: SERVICE CHARGE | C12: 0 | D12: 0 | E12: 0 | F12: 0 | G12: 0 | H12: 0 | I12: 0 | J12: 0 | K12: 0 | L12: - | M12: - | N12: - | O12: =SUM(C12:N12) -> 0
B13: ='Property Management Overview'!B13 -> AGENT FEES / COMMISSIONS | C13: 0 | D13: 0 | E13: 0 | F13: 0 | G13: 0 | H13: 0 | I13: 0 | J13: 0 | K13: 0 | L13: 0 | M13: 0 | N13: 0 | O13: =SUM(C13:N13) -> 0
B14: ='Property Management Overview'!B23 -> INSURANCE | C14: 0 | D14: 0 | E14: 0 | F14: 0 | G14: 0 | H14: 0 | I14: 0 | J14: 0 | K14: 0 | L14: 0 | M14: 0 | N14: 0 | O14: =SUM(C14:N14) -> 0
B15: ='Property Management Overview'!B15 -> INTERIOR MAINTENANCE | C15: 0 | D15: 0 | E15: 0 | F15: 0 | G15: 0 | H15: 0 | I15: 0 | J15: 0 | K15: 0 | L15: 0 | M15: 0 | N15: 0 | O15: =SUM(C15:N15) -> 0
B16: ='Property Management Overview'!B16 -> INTERIOR REPAIRS | C16: 0 | D16: 0 | E16: 0 | F16: 0 | G16: 0 | H16: 0 | I16: 0 | J16: 0 | K16: 0 | L16: 0 | M16: 0 | N16: 0 | O16: =SUM(C16:N16) -> 0
B17: ='Property Management Overview'!B17 -> HOUSEKEEPING | C17: 0 | D17: 0 | E17: 0 | F17: 0 | G17: 0 | H17: 0 | I17: 0 | J17: 0 | K17: 0 | L17: 0 | M17: 0 | N17: 0 | O17: =SUM(C17:N17) -> 0
B18: ='Property Management Overview'!B18 -> EXTERIOR MAINTENANCE | C18: 0 | D18: 0 | E18: 0 | F18: 0 | G18: 0 | H18: 0 | I18: 0 | J18: 0 | K18: 0 | L18: 0 | M18: 0 | N18: 0 | O18: =SUM(C18:N18) -> 0
B19: ='Property Management Overview'!B19 -> EXTERIOR REPAIRS | C19: 0 | D19: 0 | E19: 0 | F19: 0 | G19: 0 | H19: 0 | I19: 0 | J19: 0 | K19: 0 | L19: 0 | M19: 0 | N19: 0 | O19: =SUM(C19:N19) -> 0
B20: ='Property Management Overview'!B20 -> GROUNDSKEEPING | C20: 0 | D20: 0 | E20: 0 | F20: 0 | G20: 0 | H20: 0 | I20: 0 | J20: 0 | K20: 0 | L20: 0 | M20: 0 | N20: 0 | O20: =SUM(C20:N20) -> 0
B21: ='Property Management Overview'!B14 -> AIR+LISTRIK | C21: 0 | D21: 0 | E21: 0 | G21: 0 | H21: 0 | I21: 0 | J21: 0 | K21: 0 | L21: 0 | M21: 0 | N21: 0 | O21: =SUM(C21:N21) -> 0
B22: ='Property Management Overview'!B22 -> GAS | C22: 0 | D22: 0 | E22: 0 | F22: 0 | G22: 0 | H22: 0 | I22: 0 | J22: 0 | K22: 0 | L22: 0 | M22: 0 | N22: 0 | O22: =SUM(C22:N22) -> 0
B23: =#REF! -> #REF! | C23: 0 | D23: 0 | E23: 0 | F23: 0 | G23: 0 | H23: 0 | I23: 0 | J23: 0 | K23: 0 | L23: 0 | M23: 0 | N23: 0 | O23: =SUM(C23:N23) -> 0
B24: ='Property Management Overview'!B24 -> SEWAGE | C24: 0 | D24: 0 | E24: 0 | F24: 0 | G24: 0 | H24: 0 | I24: 0 | J24: 0 | K24: 0 | L24: 0 | M24: 0 | N24: 0 | O24: =SUM(C24:N24) -> 0
B25: ='Property Management Overview'!B25 -> REFUSE | C25: 0 | D25: 0 | E25: 0 | F25: 0 | G25: 0 | H25: 0 | I25: 0 | J25: 0 | K25: 0 | L25: 0 | M25: 0 | N25: 0 | O25: =SUM(C25:N25) -> 0
B26: ='Property Management Overview'!B26 -> CORRESPONDENCE - Postage, Stationery, Phone, Etc. | C26: 0 | D26: 0 | E26: 0 | F26: 0 | G26: 0 | H26: 0 | I26: 0 | J26: 0 | K26: 0 | L26: 0 | M26: 0 | N26: 0 | O26: =SUM(C26:N26) -> 0
B27: ='Property Management Overview'!B27 -> CARETAKER FEES / SALARY | C27: 0 | D27: 0 | E27: 0 | F27: 0 | G27: 0 | H27: 0 | I27: 0 | J27: 0 | K27: 0 | L27: 0 | M27: 0 | N27: 0 | O27: =SUM(C27:N27) -> 0
B28: ='Property Management Overview'!B28 -> TRAVEL EXPENSES | C28: 0 | D28: 0 | E28: 0 | F28: 0 | G28: 0 | H28: 0 | I28: 0 | J28: 0 | K28: 0 | L28: 0 | M28: 0 | N28: 0 | O28: =SUM(C28:N28) -> 0
B29: ='Property Management Overview'!B29 -> EQUIPMENT / APPLIANCE PURCHASES | C29: 0 | D29: 0 | E29: 0 | F29: 0 | G29: 0 | H29: 0 | I29: 0 | J29: 0 | K29: 0 | L29: 0 | M29: 0 | N29: 0 | O29: =SUM(C29:N29) -> 0
B30: ='Property Management Overview'!B30 -> EQUIPMENT / APPLIANCE RENTAL FEES | C30: 0 | D30: 0 | E30: 0 | F30: 0 | G30: 0 | H30: 0 | I30: 0 | J30: 0 | K30: 0 | L30: 0 | M30: 0 | N30: 0 | O30: =SUM(C30:N30) -> 0
B31: ='Property Management Overview'!B31 -> LAND TAX | C31: 0 | D31: 0 | E31: 0 | F31: 0 | G31: 0 | H31: 0 | I31: 0 | J31: 0 | K31: 0 | L31: 0 | M31: 0 | N31: 0 | O31: =SUM(C31:N31) -> 0
B32: ='Property Management Overview'!B32 -> BORROWING EXPENSES | C32: 0 | D32: 0 | E32: 0 | F32: 0 | G32: 0 | H32: 0 | I32: 0 | J32: 0 | K32: 0 | L32: 0 | M32: 0 | N32: 0 | O32: =SUM(C32:N32) -> 0
B33: ='Property Management Overview'!B33 -> LOAN(S) INTEREST | C33: 0 | D33: 0 | E33: 0 | F33: 0 | G33: 0 | H33: 0 | I33: 0 | J33: 0 | K33: 0 | L33: 0 | M33: 0 | N33: 0 | O33: =SUM(C33:N33) -> 0
B34: ='Property Management Overview'!B34 -> TRAVEL EXPENSES | C34: 0 | D34: 0 | E34: 0 | F34: 0 | G34: 0 | H34: 0 | I34: 0 | J34: 0 | K34: 0 | L34: 0 | M34: 0 | N34: 0 | O34: =SUM(C34:N34) -> 0
B35: ='Property Management Overview'!B35 -> OTHER | C35: 0 | D35: 0 | E35: 0 | F35: 0 | G35: 0 | H35: 0 | I35: 0 | J35: 0 | K35: 0 | L35: 0 | M35: 0 | N35: 0 | O35: =SUM(C35:N35) -> 0
... B42: ='Property Management Overview'!B42 -> OTHER | C42: 0 | D42: 0 | E42: 0 | F42: 0 | G42: 0 | H42: 0 | I42: 0 | J42: 0 | K42: 0 | L42: 0 | M42: 0 | N42: 0 | O42: =SUM(C42:N42) -> 0
B43: TOTAL EXPENSES | C43: =SUM(C11:C42) -> 0 | D43: =SUM(D11:D42) -> 0 | E43: =SUM(E11:E42) -> 0 | F43: =SUM(F11:F42) -> 0 | G43: =SUM(G11:G42) -> 0 | H43: =SUM(H11:H42) -> 0 | I43: =SUM(I11:I42) -> 0 | J43: =SUM(J11:J42) -> 0 | ... N43: =SUM(N11:N42) -> 0 | O43: =SUM(C43:N43) -> 0
B45: YEAR TO-DATE-INCOME LESS EXPENSES | C45: =C7-C43 -> 0 | D45: =D7-D43 -> 0 | E45: =E7-E43 -> 0 | F45: =F7-F43 -> 0 | G45: =G7-G43 -> 0 | H45: =H7-H43 -> 0 | I45: =I7-I43 -> 0 | J45: =J7-J43 -> 0 | ... O45: =O7-O43 -> 0

Sheet YALE 0111
B1: PROPERTY MANAGEMENT SPREADSHEET TEMPLATE
B2: YALE 0111 | C2: 123 Main Street, City, State 10001
B3: INCOME | C3: JAN | D3: FEB | E3: MAR | F3: APR | G3: MAY | H3: JUN | I3: JUL | J3: AUG | K3: SEPT | L3: OCT | M3: NOV | N3: DEC | O3: YR TOTAL
B4: MULTI-PROPERTY INCOME OVERVIEW
B5: ='Property Management Overview'!B5 -> RENTAL INCOME | C5: 2085000 | D5: 2085000 | E5: 2085000 | F5: 2085000 | G5: 2085000 | H5: 2085000 | I5: 0 | J5: 0 | K5: 0 | L5: 0 | M5: 0 | N5: 0 | O5: =SUM(C5:N5) -> 12510000 | Q5: bilang sukron next 25jt nett
B6: ='Property Management Overview'!B6 -> OTHER RENTAL INCOME – Late Fees, Etc. | C6: 0 | D6: 0 | E6: 0 | F6: 0 | G6: 0 | H6: 0 | I6: 0 | J6: 0 | K6: 0 | L6: 0 | M6: 0 | N6: 0 | O6: =SUM(C6:N6) -> 0
B7: GROSS RENTAL INCOME | C7: =SUM(C5:C6) -> 2085000 | D7: =SUM(D5:D6) -> 2085000 | E7: =SUM(E5:E6) -> 2085000 | F7: =SUM(F5:F6) -> 2085000 | G7: =SUM(G5:G6) -> 2085000 | H7: =SUM(H5:H6) -> 2085000 | I7: =SUM(I5:I6) -> 0 | J7: =SUM(J5:J6) -> 0 | ... N7: =SUM(N5:N6) -> 0 | O7: =SUM(C7:N7) -> 12510000
B9: EXPENSES | C9: JAN | D9: FEB | E9: MAR | F9: APR | G9: MAY | H9: JUN | I9: JUL | J9: AUG | K9: SEPT | L9: OCT | M9: NOV | N9: DEC | O9: YR TOTAL
B10: ='Property Management Overview'!B10 -> MULTI-PROPERTY EXPENSES OVERVIEW
B11: ='Property Management Overview'!B11 -> MARKETING / ADVERTISING | C11: 0 | D11: 0 | E11: 0 | F11: 0 | G11: 0 | H11: 0 | I11: 0 | J11: 0 | K11: 0 | L11: 0 | M11: 0 | N11: 0 | O11: =SUM(C11:N11) -> 0
B12: ='Property Management Overview'!B12 -> SERVICE CHARGE | C12: 0 | D12: 0 | E12: 0 | F12: 0 | G12: 0 | H12: 0 | I12: 0 | J12: 0 | K12: 0 | L12: 0 | M12: 0 | N12: 0 | O12: =SUM(C12:N12) -> 0
B13: ='Property Management Overview'!B13 -> AGENT FEES / COMMISSIONS | C13: 210000 | D13: 210000 | E13: 210000 | F13: 210000 | G13: 210000 | H13: 210000 | I13: 0 | J13: 0 | K13: 0 | L13: 0 | M13: 0 | N13: 0 | O13: =SUM(C13:N13) -> 1260000
B14: ='Property Management Overview'!B23 -> INSURANCE | C14: 0 | D14: 0 | E14: 0 | F14: 0 | G14: 0 | H14: 0 | I14: 0 | J14: 0 | K14: 0 | L14: 0 | M14: 0 | N14: 0 | O14: =SUM(C14:N14) -> 0
B15: ='Property Management Overview'!B15 -> INTERIOR MAINTENANCE | C15: 0 | D15: 0 | E15: 0 | F15: 0 | G15: 0 | H15: 0 | I15: 0 | J15: 0 | K15: 0 | L15: 0 | M15: 0 | N15: 0 | O15: =SUM(C15:N15) -> 0
B16: ='Property Management Overview'!B16 -> INTERIOR REPAIRS | C16: 0 | D16: 0 | E16: 0 | F16: 0 | G16: 0 | H16: 0 | I16: 0 | J16: 0 | K16: 0 | L16: 0 | M16: 0 | N16: 0 | O16: =SUM(C16:N16) -> 0
B17: ='Property Management Overview'!B17 -> HOUSEKEEPING | C17: 0 | D17: 0 | E17: 0 | F17: 0 | G17: 0 | H17: 0 | I17: 0 | J17: 0 | K17: 0 | L17: 0 | M17: 0 | N17: 0 | O17: =SUM(C17:N17) -> 0
B18: ='Property Management Overview'!B18 -> EXTERIOR MAINTENANCE | C18: 0 | D18: 0 | E18: 0 | F18: 0 | G18: 0 | H18: 0 | I18: 0 | J18: 0 | K18: 0 | L18: 0 | M18: 0 | N18: 0 | O18: =SUM(C18:N18) -> 0
B19: ='Property Management Overview'!B19 -> EXTERIOR REPAIRS | C19: 0 | D19: 0 | E19: 0 | F19: 0 | G19: 0 | H19: 0 | I19: 0 | J19: 0 | K19: 0 | L19: 0 | M19: 0 | N19: 0 | O19: =SUM(C19:N19) -> 0
B20: ='Property Management Overview'!B20 -> GROUNDSKEEPING | C20: 0 | D20: 0 | E20: 0 | F20: 0 | G20: 0 | H20: 0 | I20: 0 | J20: 0 | K20: 0 | L20: 0 | M20: 0 | N20: 0 | O20: =SUM(C20:N20) -> 0
B21: ='Property Management Overview'!B14 -> AIR+LISTRIK | C21: 0 | D21: 0 | E21: 0 | F21: 0 | G21: 0 | H21: 0 | I21: 0 | J21: - | K21: 0 | L21: 0 | M21: 0 | N21: 0 | O21: =SUM(C21:N21) -> 0
B22: ='Property Management Overview'!B22 -> GAS | C22: 0 | D22: 0 | E22: 0 | F22: 0 | G22: 0 | H22: 0 | I22: 0 | J22: 0 | K22: 0 | L22: 0 | M22: 0 | N22: 0 | O22: =SUM(C22:N22) -> 0
B23: =#REF! -> #REF! | C23: 0 | D23: 0 | E23: 0 | F23: 0 | G23: 0 | H23: 0 | I23: 0 | J23: 0 | K23: 0 | L23: 0 | M23: 0 | N23: 0 | O23: =SUM(C23:N23) -> 0
B24: ='Property Management Overview'!B24 -> SEWAGE | C24: 0 | D24: 0 | E24: 0 | F24: 0 | G24: 0 | H24: 0 | I24: 0 | J24: 0 | K24: 0 | L24: 0 | M24: 0 | N24: 0 | O24: =SUM(C24:N24) -> 0
B25: ='Property Management Overview'!B25 -> REFUSE | C25: 0 | D25: 0 | E25: 0 | F25: 0 | G25: 0 | H25: 0 | I25: 0 | J25: 0 | K25: 0 | L25: 0 | M25: 0 | N25: 0 | O25: =SUM(C25:N25) -> 0
B26: ='Property Management Overview'!B26 -> CORRESPONDENCE - Postage, Stationery, Phone, Etc. | C26: 0 | D26: 0 | E26: 0 | F26: 0 | G26: 0 | H26: 0 | I26: 0 | J26: 0 | K26: 0 | L26: 0 | M26: 0 | N26: 0 | O26: =SUM(C26:N26) -> 0
B27: ='Property Management Overview'!B27 -> CARETAKER FEES / SALARY | C27: 0 | D27: 0 | E27: 0 | F27: 0 | G27: 0 | H27: 0 | I27: 0 | J27: 0 | K27: 0 | L27: 0 | M27: 0 | N27: 0 | O27: =SUM(C27:N27) -> 0
B28: ='Property Management Overview'!B28 -> TRAVEL EXPENSES | C28: 0 | D28: 0 | E28: 0 | F28: 0 | G28: 0 | H28: 0 | I28: 0 | J28: 0 | K28: 0 | L28: 0 | M28: 0 | N28: 0 | O28: =SUM(C28:N28) -> 0
B29: ='Property Management Overview'!B29 -> EQUIPMENT / APPLIANCE PURCHASES | C29: 0 | D29: 0 | E29: 0 | F29: 0 | G29: 0 | H29: 0 | I29: 0 | J29: 0 | K29: 0 | L29: 0 | M29: 0 | N29: 0 | O29: =SUM(C29:N29) -> 0
B30: ='Property Management Overview'!B30 -> EQUIPMENT / APPLIANCE RENTAL FEES | C30: 0 | D30: 0 | E30: 0 | F30: 0 | G30: 0 | H30: 0 | I30: 0 | J30: 0 | K30: 0 | L30: 0 | M30: 0 | N30: 0 | O30: =SUM(C30:N30) -> 0
B31: ='Property Management Overview'!B31 -> LAND TAX | C31: 0 | D31: 0 | E31: 0 | F31: 0 | G31: 240675 | H31: 0 | I31: 0 | J31: 0 | K31: 0 | L31: 0 | M31: 0 | N31: 0 | O31: =SUM(C31:N31) -> 240675
B32: ='Property Management Overview'!B32 -> BORROWING EXPENSES | C32: 0 | D32: 0 | E32: 0 | F32: 0 | G32: 0 | H32: 0 | I32: 0 | J32: 0 | K32: 0 | L32: 0 | M32: 0 | N32: 0 | O32: =SUM(C32:N32) -> 0
B33: ='Property Management Overview'!B33 -> LOAN(S) INTEREST | C33: 0 | D33: 0 | E33: 0 | F33: 0 | G33: 0 | H33: 0 | I33: 0 | J33: 0 | K33: 0 | L33: 0 | M33: 0 | N33: 0 | O33: =SUM(C33:N33) -> 0
B34: ='Property Management Overview'!B34 -> TRAVEL EXPENSES | C34: 0 | D34: 0 | E34: 0 | F34: 0 | G34: 0 | H34: 0 | I34: 0 | J34: 0 | K34: 0 | L34: 0 | M34: 0 | N34: 0 | O34: =SUM(C34:N34) -> 0
B35: ='Property Management Overview'!B35 -> OTHER | C35: 0 | D35: 0 | E35: 0 | F35: 0 | G35: 0 | H35: 0 | I35: 0 | J35: 0 | K35: 0 | L35: 0 | M35: 0 | N35: 0 | O35: =SUM(C35:N35) -> 0
... B42: ='Property Management Overview'!B42 -> OTHER | C42: 0 | D42: 0 | E42: 0 | F42: 0 | G42: 0 | H42: 0 | I42: 0 | J42: 0 | K42: 0 | L42: 0 | M42: 0 | N42: 0 | O42: =SUM(C42:N42) -> 0
B43: TOTAL EXPENSES | C43: =SUM(C11:C42) -> 210000 | D43: =SUM(D11:D42) -> 210000 | E43: =SUM(E11:E42) -> 210000 | F43: =SUM(F11:F42) -> 210000 | G43: =SUM(G11:G42) -> 450675 | H43: =SUM(H11:H42) -> 210000 | I43: =SUM(I11:I42) -> 0 | J43: =SUM(J11:J42) -> 0 | ... N43: =SUM(N11:N42) -> 0 | O43: =SUM(C43:N43) -> 1500675
B45: YEAR-TO-DATE INCOME LESS EXPENSES | C45: =C7-C43 -> 1875000 | D45: =D7-D43 -> 1875000 | E45: =E7-E43 -> 1875000 | F45: =F7-F43 -> 1875000 | G45: =G7-G43 -> 1634325 | H45: =H7-H43 -> 1875000 | I45: =I7-I43 -> 0 | J45: =J7-J43 -> 0 | ... O45: =O7-O43 -> 11009325

Sheet YALE 0727
B1: PROPERTY MANAGEMENT SPREADSHEET TEMPLATE
B2: YALE 0727 | C2: 123 Main Street, City, State 10001
B3: INCOME | C3: JAN | D3: FEB | E3: MAR | F3: APR | G3: MAY | H3: JUN | I3: JUL | J3: AUG | K3: SEPT | L3: OCT | M3: NOV | N3: DEC | O3: YR TOTAL
B4: MULTI-PROPERTY INCOME OVERVIEW | C4: 8/1-8/2 | D4: 8/2-8/3
B5: ='Property Management Overview'!B5 -> RENTAL INCOME | C5: 2500000 | D5: 2500000 | O5: =SUM(C5:N5) -> 5000000
B6: ='Property Management Overview'!B6 -> OTHER RENTAL INCOME – Late Fees, Etc. | C6: 0 | D6: 0 | E6: 0 | F6: 0 | G6: 0 | H6: 0 | I6: 0 | J6: 0 | K6: 0 | L6: 0 | M6: 0 | N6: 0 | O6: =SUM(C6:N6) -> 0
B7: GROSS RENTAL INCOME | C7: =SUM(C5:C6) -> 2500000 | D7: =SUM(D5:D6) -> 2500000 | E7: =SUM(E5:E6) -> 0 | F7: =SUM(F5:F6) -> 0 | G7: =SUM(G5:G6) -> 0 | H7: =SUM(H5:H6) -> 0 | I7: =SUM(I5:I6) -> 0 | J7: =SUM(J5:J6) -> 0 | ... N7: =SUM(N5:N6) -> 0 | O7: =SUM(C7:N7) -> 5000000
B9: EXPENSES | C9: JAN | D9: FEB | E9: MAR | F9: APR | G9: MAY | H9: JUN | I9: JUL | J9: AUG | K9: SEPT | L9: OCT | M9: NOV | N9: DEC | O9: YR TOTAL
B10: ='Property Management Overview'!B10 -> MULTI-PROPERTY EXPENSES OVERVIEW | I10: parking access | K10: 31/08/2023 - 30/09/2023
B11: ='Property Management Overview'!B11 -> MARKETING / ADVERTISING | C11: 0 | D11: 0 | E11: 0 | F11: 0 | G11: 0 | H11: 0 | I11: 0 | J11: 0 | K11: 0 | L11: 0 | M11: 0 | N11: 0 | O11: =SUM(C11:N11) -> 0
B12: ='Property Management Overview'!B12 -> SERVICE CHARGE | C12: 300000 | D12: 300000 | E12: 300000 | O12: =SUM(C12:N12) -> 900000
B13: ='Property Management Overview'!B13 -> AGENT FEES / COMMISSIONS | C13: 0 | D13: 0 | E13: 0 | F13: 0 | G13: 0 | H13: 0 | I13: 0 | J13: 0 | K13: 0 | L13: 0 | M13: 0 | N13: 0 | O13: =SUM(C13:N13) -> 0
B14: ='Property Management Overview'!B23 -> INSURANCE | C14: 0 | D14: 0 | E14: 0 | F14: 0 | G14: 0 | H14: 0 | I14: 0 | J14: 0 | K14: 0 | L14: 0 | M14: 0 | N14: 0 | O14: =SUM(C14:N14) -> 0
B15: ='Property Management Overview'!B15 -> INTERIOR MAINTENANCE | C15: 0 | D15: 0 | E15: 0 | F15: 0 | G15: 0 | H15: 0 | I15: 0 | J15: 0 | K15: 0 | L15: 0 | M15: 0 | N15: 0 | O15: =SUM(C15:N15) -> 0
B16: ='Property Management Overview'!B16 -> INTERIOR REPAIRS | C16: 0 | D16: 0 | E16: 0 | F16: 0 | G16: 0 | H16: 0 | I16: 0 | J16: 0 | K16: 0 | L16: 0 | M16: 0 | N16: 0 | O16: =SUM(C16:N16) -> 0
B17: ='Property Management Overview'!B17 -> HOUSEKEEPING | C17: 0 | D17: 0 | E17: 0 | F17: 0 | G17: 0 | H17: 0 | I17: 0 | J17: 0 | K17: 0 | L17: 0 | M17: 0 | N17: 0 | O17: =SUM(C17:N17) -> 0
B18: ='Property Management Overview'!B18 -> EXTERIOR MAINTENANCE | C18: 0 | D18: 0 | E18: 0 | F18: 0 | G18: 0 | H18: 0 | I18: 0 | J18: 0 | K18: 0 | L18: 0 | M18: 0 | N18: 0 | O18: =SUM(C18:N18) -> 0
B19: ='Property Management Overview'!B19 -> EXTERIOR REPAIRS | C19: 0 | D19: 0 | E19: 0 | F19: 0 | G19: 0 | H19: 0 | I19: 0 | J19: 0 | K19: 0 | L19: 0 | M19: 0 | N19: 0 | O19: =SUM(C19:N19) -> 0
B20: ='Property Management Overview'!B20 -> GROUNDSKEEPING | C20: 0 | D20: 0 | E20: 0 | F20: 0 | G20: 0 | H20: 0 | I20: 0 | J20: 0 | K20: 0 | L20: 0 | M20: 0 | N20: 0 | O20: =SUM(C20:N20) -> 0
B21: ='Property Management Overview'!B14 -> AIR+LISTRIK | C21: 0 | D21: 0 | E21: 0 | F21: 0 | G21: 0 | H21: 0 | I21: 0 | J21: 0 | K21: 0 | L21: 0 | M21: 0 | O21: =SUM(C21:N21) -> 0
B22: ='Property Management Overview'!B22 -> GAS | C22: 0 | D22: 0 | E22: 0 | F22: 0 | G22: 0 | H22: 0 | I22: 0 | J22: 0 | K22: 0 | L22: 0 | M22: 0 | N22: 0 | O22: =SUM(C22:N22) -> 0
B23: =#REF! -> #REF! | C23: 0 | D23: 0 | E23: 0 | F23: 0 | G23: 0 | H23: 0 | I23: 0 | J23: 0 | K23: 0 | L23: 0 | M23: 0 | N23: 0 | O23: =SUM(C23:N23) -> 0
B24: ='Property Management Overview'!B24 -> SEWAGE | C24: 0 | D24: 0 | E24: 0 | F24: 0 | G24: 0 | H24: 0 | I24: 0 | J24: 0 | K24: 0 | L24: 0 | M24: 0 | N24: 0 | O24: =SUM(C24:N24) -> 0
B25: ='Property Management Overview'!B25 -> REFUSE | C25: 0 | D25: 0 | E25: 0 | F25: 0 | G25: 0 | H25: 0 | I25: 0 | J25: 0 | K25: 0 | L25: 0 | M25: 0 | N25: 0 | O25: =SUM(C25:N25) -> 0
B26: ='Property Management Overview'!B26 -> CORRESPONDENCE - Postage, Stationery, Phone, Etc. | C26: 0 | D26: 0 | E26: 0 | F26: 0 | G26: 0 | H26: 0 | I26: 0 | J26: 0 | K26: 0 | L26: 0 | M26: 0 | N26: 0 | O26: =SUM(C26:N26) -> 0
B27: ='Property Management Overview'!B27 -> CARETAKER FEES / SALARY | C27: 0 | D27: 0 | E27: 0 | F27: 0 | G27: 0 | H27: 0 | I27: 0 | J27: 0 | K27: 0 | L27: 0 | M27: 0 | N27: 0 | O27: =SUM(C27:N27) -> 0
B28: ='Property Management Overview'!B28 -> TRAVEL EXPENSES | C28: 0 | D28: 0 | E28: 0 | F28: 0 | G28: 0 | H28: 0 | I28: 0 | J28: 0 | K28: 0 | L28: 0 | M28: 0 | N28: 0 | O28: =SUM(C28:N28) -> 0
B29: ='Property Management Overview'!B29 -> EQUIPMENT / APPLIANCE PURCHASES | C29: 0 | D29: 0 | E29: 0 | F29: 0 | G29: 0 | H29: 0 | I29: 0 | J29: 310000 | K29: 0 | L29: 0 | M29: 0 | N29: 0 | O29: =SUM(C29:N29) -> 310000
B30: ='Property Management Overview'!B30 -> EQUIPMENT / APPLIANCE RENTAL FEES | C30: 0 | D30: 0 | E30: 0 | F30: 0 | G30: 0 | H30: 0 | I30: 0 | J30: 0 | K30: 0 | L30: 0 | M30: 0 | N30: 0 | O30: =SUM(C30:N30) -> 0
B31: ='Property Management Overview'!B31 -> LAND TAX | C31: 0 | D31: 0 | E31: 0 | F31: 0 | G31: 240675 | H31: 0 | I31: 0 | J31: 0 | K31: 0 | L31: 0 | M31: 0 | N31: 0 | O31: =SUM(C31:N31) -> 240675
B32: ='Property Management Overview'!B32 -> BORROWING EXPENSES | C32: 0 | D32: 0 | E32: 0 | F32: 0 | G32: 0 | H32: 0 | I32: 0 | J32: 0 | K32: 0 | L32: 0 | M32: 0 | N32: 0 | O32: =SUM(C32:N32) -> 0
B33: ='Property Management Overview'!B33 -> LOAN(S) INTEREST | C33: 0 | D33: 0 | E33: 0 | F33: 0 | G33: 0 | H33: 0 | I33: 0 | J33: 0 | K33: 0 | L33: 0 | M33: 0 | N33: 0 | O33: =SUM(C33:N33) -> 0
B34: ='Property Management Overview'!B34 -> TRAVEL EXPENSES | C34: 0 | D34: 0 | E34: 0 | F34: 0 | G34: 0 | H34: 0 | I34: 0 | J34: 0 | K34: 0 | L34: 0 | M34: 0 | N34: 0 | O34: =SUM(C34:N34) -> 0
B35: ='Property Management Overview'!B35 -> OTHER | C35: 0 | D35: 0 | E35: 0 | F35: 0 | G35: 0 | H35: 0 | I35: 0 | J35: 0 | K35: 0 | L35: 0 | M35: 0 | N35: 0 | O35: =SUM(C35:N35) -> 0
B36: ='Property Management Overview'!B36 -> OTHER | C36: - | D36: 0 | E36: 0 | F36: 0 | G36: 0 | H36: 0 | I36: 0 | J36: 0 | K36: 0 | L36: 0 | M36: 0 | N36: 0 | O36: =SUM(C36:N36) -> 0
B37: ='Property Management Overview'!B37 -> OTHER | C37: 0 | D37: 0 | E37: 0 | F37: 0 | G37: 0 | H37: 0 | I37: 0 | J37: 0 | K37: 0 | L37: 0 | M37: 0 | N37: 0 | O37: =SUM(C37:N37) -> 0
B38: ='Property Management Overview'!B38 -> OTHER | C38: 0 | D38: 0 | E38: 0 | F38: 0 | G38: 0 | H38: 0 | I38: 0 | J38: 0 | K38: 0 | L38: 0 | M38: 0 | N38: 0 | O38: =SUM(C38:N38) -> 0
B39: ='Property Management Overview'!B39 -> OTHER | C39: 0 | D39: 0 | E39: 0 | F39: 0 | G39: 0 | H39: 0 | I39: 0 | J39: 0 | K39: 0 | L39: 0 | M39: 0 | N39: 0 | O39: =SUM(C39:N39) -> 0
B40: ='Property Management Overview'!B40 -> OTHER | C40: 0 | D40: 0 | E40: 0 | F40: 0 | G40: 0 | H40: 0 | I40: 0 | J40: 0 | K40: 0 | L40: 0 | M40: 0 | N40: 0 | O40: =SUM(C40:N40) -> 0
B41: ='Property Management Overview'!B41 -> OTHER | C41: 0 | D41: 0 | E41: 0 | F41: 0 | G41: 0 | H41: 0 | I41: 0 | J41: 0 | K41: 0 | L41: 0 | M41: 0 | N41: 0 | O41: =SUM(C41:N41) -> 0
B42: ='Property Management Overview'!B42 -> OTHER | C42: 0 | D42: 0 | E42: 0 | F42: 0 | G42: 0 | H42: 0 | I42: 0 | J42: 0 | K42: 0 | L42: 0 | M42: 0 | N42: 0 | O42: =SUM(C42:N42) -> 0
B43: TOTAL EXPENSES | C43: =SUM(C11:C42) -> 300000 | D43: =SUM(D11:D42) -> 300000 | E43: =SUM(E11:E42) -> 300000 | F43: =SUM(F11:F42) -> 0 | G43: =SUM(G11:G42) -> 240675 | H43: =SUM(H11:H42) -> 0 | I43: =SUM(I11:I42) -> 0 | J43: =SUM(J11:J42) -> 310000 | ... N43: =SUM(N11:N42) -> 0 | O43: =SUM(C43:N43) -> 1450675
B45: YEAR-TO-DATE INCOME LESS EXPENSES | C45: =C7-C43 -> 2200000 | D45: =D7-D43 -> 2200000 | E45: =E7-E43 -> -300000 | F45: =F7-F43 -> 0 | G45: =G7-G43 -> -240675 | H45: =H7-H43 -> 0 | I45: =I7-I43 -> 0 | J45: =J7-J43 -> -310000 | ... O45: =O7-O43 -> 3549325

Sheet YALE 0728
B1: PROPERTY MANAGEMENT SPREADSHEET TEMPLATE
B2: YALE 0728 | C2: 123 Main Street, City, State 10001
B3: INCOME | C3: JAN | D3: FEB | E3: MAR | F3: APR | G3: MAY | H3: JUN | I3: JUL | J3: AUG | K3: SEPT | L3: OCT | M3: NOV | N3: DEC | O3: YR TOTAL
B4: MULTI-PROPERTY INCOME OVERVIEW | F4: 0 | G4: 0 | H4: 0 | J4: 0 | L4: 0 | M4: 0
B5: ='Property Management Overview'!B5 -> RENTAL INCOME | O5: =SUM(C5:N5) -> 0
B6: ='Property Management Overview'!B6 -> OTHER RENTAL INCOME – Late Fees, Etc. | C6: 0 | D6: 0 | E6: 0 | F6: 0 | G6: 0 | H6: 0 | I6: 0 | J6: 0 | K6: 0 | L6: 0 | M6: 0 | N6: 0 | O6: =SUM(C6:N6) -> 0
B7: GROSS RENTAL INCOME | C7: =SUM(C5:C6) -> 0 | D7: =SUM(D5:D6) -> 0 | E7: =SUM(E5:E6) -> 0 | F7: =SUM(F5:F6) -> 0 | G7: =SUM(G5:G6) -> 0 | H7: =SUM(H5:H6) -> 0 | I7: =SUM(I5:I6) -> 0 | J7: =SUM(J5:J6) -> 0 | ... N7: =SUM(N5:N6) -> 0 | O7: =SUM(C7:N7) -> 0
B9: EXPENSES | C9: JAN | D9: FEB | E9: MAR | F9: APR | G9: MAY | H9: JUN | I9: JUL | J9: AUG | K9: SEPT | L9: OCT | M9: NOV | N9: DEC | O9: YR TOTAL
B10: ='Property Management Overview'!B10 -> MULTI-PROPERTY EXPENSES OVERVIEW | K10: 0 | L10: 0
B11: ='Property Management Overview'!B11 -> MARKETING / ADVERTISING | C11: 0 | D11: 0 | E11: 0 | F11: 0 | G11: 0 | H11: 0 | I11: 0 | J11: 0 | K11: 0 | L11: 0 | M11: 0 | N11: 0 | O11: =SUM(C11:N11) -> 0
B12: ='Property Management Overview'!B12 -> SERVICE CHARGE | C12: 0 | D12: 0 | E12: 0 | F12: 0 | G12: 0 | H12: 0 | I12: 0 | J12: 0 | K12: 0 | L12: 0 | M12: 0 | N12: 0 | O12: =SUM(C12:N12) -> 0
B13: ='Property Management Overview'!B13 -> AGENT FEES / COMMISSIONS | C13: 0 | D13: 0 | E13: 0 | F13: 0 | G13: 0 | H13: 0 | I13: 0 | J13: 0 | K13: 0 | L13: 0 | M13: 0 | N13: 0 | O13: =SUM(C13:N13) -> 0
B14: ='Property Management Overview'!B23 -> INSURANCE | C14: 0 | D14: 0 | E14: 0 | F14: 0 | G14: 0 | H14: 0 | I14: 0 | J14: 0 | K14: 0 | L14: 0 | M14: 0 | N14: 0 | O14: =SUM(C14:N14) -> 0
B15: ='Property Management Overview'!B15 -> INTERIOR MAINTENANCE | C15: 0 | D15: 0 | E15: 0 | F15: 0 | G15: 0 | H15: 0 | I15: 0 | J15: 0 | K15: 0 | L15: 0 | M15: 0 | N15: 0 | O15: =SUM(C15:N15) -> 0
B16: ='Property Management Overview'!B16 -> INTERIOR REPAIRS | C16: 0 | D16: 0 | E16: 0 | F16: 0 | G16: 0 | H16: 0 | I16: 0 | J16: 0 | K16: 0 | L16: 0 | M16: 0 | N16: 0 | O16: =SUM(C16:N16) -> 0
B17: ='Property Management Overview'!B17 -> HOUSEKEEPING | C17: 0 | D17: 0 | E17: 0 | F17: 0 | G17: 0 | H17: 0 | I17: 0 | J17: 0 | K17: 0 | L17: 0 | M17: 0 | N17: 0 | O17: =SUM(C17:N17) -> 0
B18: ='Property Management Overview'!B18 -> EXTERIOR MAINTENANCE | C18: 0 | D18: 0 | E18: 0 | F18: 0 | G18: 0 | H18: 0 | I18: 0 | J18: 0 | K18: 0 | L18: 0 | M18: 0 | N18: 0 | O18: =SUM(C18:N18) -> 0
B19: ='Property Management Overview'!B19 -> EXTERIOR REPAIRS | C19: 0 | D19: 0 | E19: 0 | F19: 0 | G19: 0 | H19: 0 | I19: 0 | J19: 0 | K19: 0 | L19: 0 | M19: 0 | N19: 0 | O19: =SUM(C19:N19) -> 0
B20: ='Property Management Overview'!B20 -> GROUNDSKEEPING | C20: 0 | D20: 0 | E20: 0 | F20: 0 | G20: 0 | H20: 0 | I20: 0 | J20: 0 | K20: 0 | L20: 0 | M20: 0 | N20: 0 | O20: =SUM(C20:N20) -> 0
B21: ='Property Management Overview'!B14 -> AIR+LISTRIK | C21: 0 | D21: 0 | E21: 0 | F21: 0 | G21: 0 | H21: 0 | I21: 0 | J21: 0 | K21: - | L21: 0 | M21: 0 | N21: 0 | O21: =SUM(C21:N21) -> 0
B22: ='Property Management Overview'!B22 -> GAS | C22: 0 | D22: 0 | E22: 0 | F22: 0 | G22: 0 | H22: 0 | I22: 0 | J22: 0 | K22: 0 | L22: 0 | M22: 0 | N22: 0 | O22: =SUM(C22:N22) -> 0
B23: =#REF! -> #REF! | C23: 0 | D23: 0 | E23: 0 | F23: 0 | G23: 0 | H23: 0 | I23: 0 | J23: 0 | K23: 0 | L23: 0 | M23: 0 | N23: 0 | O23: =SUM(C23:N23) -> 0
B24: ='Property Management Overview'!B24 -> SEWAGE | C24: 0 | D24: 0 | E24: 0 | F24: 0 | G24: 0 | H24: 0 | I24: 0 | J24: 0 | K24: 0 | L24: 0 | M24: 0 | N24: 0 | O24: =SUM(C24:N24) -> 0
B25: ='Property Management Overview'!B25 -> REFUSE | C25: 0 | D25: 0 | E25: 0 | F25: 0 | G25: 0 | H25: 0 | I25: 0 | J25: 0 | K25: 0 | L25: 0 | M25: 0 | N25: 0 | O25: =SUM(C25:N25) -> 0
B26: ='Property Management Overview'!B26 -> CORRESPONDENCE - Postage, Stationery, Phone, Etc. | C26: 0 | D26: 0 | E26: 0 | F26: 0 | G26: 0 | H26: 0 | I26: 0 | J26: 0 | K26: 0 | L26: 0 | M26: 0 | N26: 0 | O26: =SUM(C26:N26) -> 0
B27: ='Property Management Overview'!B27 -> CARETAKER FEES / SALARY | C27: 0 | D27: 0 | E27: 0 | F27: 0 | G27: 0 | H27: 0 | I27: 0 | J27: 0 | K27: 0 | L27: 0 | M27: 0 | N27: 0 | O27: =SUM(C27:N27) -> 0
B28: ='Property Management Overview'!B28 -> TRAVEL EXPENSES | C28: 0 | D28: 0 | E28: 0 | F28: 0 | G28: 0 | H28: 0 | I28: 0 | J28: 0 | K28: 0 | L28: 0 | M28: 0 | N28: 0 | O28: =SUM(C28:N28) -> 0
B29: ='Property Management Overview'!B29 -> EQUIPMENT / APPLIANCE PURCHASES | C29: 0 | D29: 0 | E29: 0 | F29: 0 | G29: 0 | H29: 0 | I29: 0 | J29: 0 | K29: 0 | L29: 0 | M29: 0 | N29: 0 | O29: =SUM(C29:N29) -> 0
B30: ='Property Management Overview'!B30 -> EQUIPMENT / APPLIANCE RENTAL FEES | C30: 0 | D30: 0 | E30: 0 | F30: 0 | G30: 0 | H30: 0 | I30: 0 | J30: 0 | K30: 0 | L30: 0 | M30: 0 | N30: 0 | O30: =SUM(C30:N30) -> 0
B31: ='Property Management Overview'!B31 -> LAND TAX | C31: 0 | D31: 0 | E31: 0 | F31: 0 | G31: 240675 | H31: 0 | I31: 0 | J31: 0 | K31: 0 | L31: 0 | M31: 0 | N31: 0 | O31: =SUM(C31:N31) -> 240675
B32: ='Property Management Overview'!B32 -> BORROWING EXPENSES | C32: 0 | D32: 0 | E32: 0 | F32: 0 | G32: 0 | H32: 0 | I32: 0 | J32: 0 | K32: 0 | L32: 0 | M32: 0 | N32: 0 | O32: =SUM(C32:N32) -> 0
B33: ='Property Management Overview'!B33 -> LOAN(S) INTEREST | C33: 0 | D33: 0 | E33: 0 | F33: 0 | G33: 0 | H33: 0 | I33: 0 | J33: 0 | K33: 0 | L33: 0 | M33: 0 | N33: 0 | O33: =SUM(C33:N33) -> 0
B34: ='Property Management Overview'!B34 -> TRAVEL EXPENSES | C34: 0 | D34: 0 | E34: 0 | F34: 0 | G34: 0 | H34: 0 | I34: 0 | J34: 0 | K34: 0 | L34: 0 | M34: 0 | N34: 0 | O34: =SUM(C34:N34) -> 0
B35: ='Property Management Overview'!B35 -> OTHER | C35: 0 | D35: 0 | E35: 0 | F35: 0 | G35: 0 | H35: 0 | I35: 0 | J35: 0 | K35: 0 | L35: 0 | M35: 0 | N35: 0 | O35: =SUM(C35:N35) -> 0
... B42: ='Property Management Overview'!B42 -> OTHER | C42: 0 | D42: 0 | E42: 0 | F42: 0 | G42: 0 | H42: 0 | I42: 0 | J42: 0 | K42: 0 | L42: 0 | M42: 0 | N42: 0 | O42: =SUM(C42:N42) -> 0
B43: TOTAL EXPENSES | C43: =SUM(C11:C42) -> 0 | D43: =SUM(D11:D42) -> 0 | E43: =SUM(E11:E42) -> 0 | F43: =SUM(F11:F42) -> 0 | G43: =SUM(G11:G42) -> 240675 | H43: =SUM(H11:H42) -> 0 | I43: =SUM(I11:I42) -> 0 | J43: =SUM(J11:J42) -> 0 | ... N43: =SUM(N11:N42) -> 0 | O43: =SUM(C43:N43) -> 240675
B45: YEAR-TO-DATE INCOME LESS EXPENSES | C45: =C7-C43 -> 0 | D45: =D7-D43 -> 0 | E45: =E7-E43 -> 0 | F45: =F7-F43 -> 0 | G45: =G7-G43 -> -240675 | H45: =H7-H43 -> 0 | I45: =I7-I43 -> 0 | J45: =J7-J43 -> 0 | ... O45: =O7-O43 -> -240675

Sheet Amega Crown A8-10
B1: PROPERTY MANAGEMENT SPREADSHEET TEMPLATE
B2: Amega Crown A8-10 | C2: 123 Main Street, City, State 10001
B3: INCOME | C3: JAN | D3: FEB | E3: MAR | F3: APR | G3: MAY | H3: JUN | I3: JUL | J3: AUG | K3: SEPT | L3: OCT | M3: NOV | N3: DEC | O3: YR TOTAL
B4: MULTI-PROPERTY INCOME OVERVIEW
B5: ='Property Management Overview'!B5 -> RENTAL INCOME | C5: 1000000 | D5: 1000000 | O5: =SUM(C5:N5) -> 2000000
B6: ='Property Management Overview'!B6 -> OTHER RENTAL INCOME – Late Fees, Etc. | O6: =SUM(C6:N6) -> 0
B7: GROSS RENTAL INCOME | C7: =SUM(C5:C6) -> 1000000 | D7: =SUM(D5:D6) -> 1000000 | E7: =SUM(E5:E6) -> 0 | F7: =SUM(F5:F6) -> 0 | G7: =SUM(G5:G6) -> 0 | H7: =SUM(H5:H6) -> 0 | I7: =SUM(I5:I6) -> 0 | J7: =SUM(J5:J6) -> 0 | ... N7: =SUM(N5:N6) -> 0 | O7: =SUM(C7:N7) -> 2000000
B9: EXPENSES | C9: JAN | D9: FEB | E9: MAR | F9: APR | G9: MAY | H9: JUN | I9: JUL | J9: AUG | K9: SEPT | L9: OCT | M9: NOV | N9: DEC | O9: YR TOTAL
B10: ='Property Management Overview'!B10 -> MULTI-PROPERTY EXPENSES OVERVIEW
B11: ='Property Management Overview'!B11 -> MARKETING / ADVERTISING | O11: =SUM(C11:N11) -> 0
B12: ='Property Management Overview'!B12 -> SERVICE CHARGE | O12: =SUM(C12:N12) -> 0
B13: ='Property Management Overview'!B13 -> AGENT FEES / COMMISSIONS | C13: 100000 | D13: 100000 | E13: 0 | F13: 0 | G13: 0 | H13: 0 | I13: 0 | J13: 0 | K13: 0 | L13: 0 | M13: 0 | N13: 0 | O13: =SUM(C13:N13) -> 200000
B14: ='Property Management Overview'!B23 -> INSURANCE | C14: 0 | D14: 0 | E14: 0 | F14: 0 | G14: 0 | H14: 0 | I14: 0 | J14: 0 | K14: 0 | L14: 0 | M14: 0 | N14: 0 | O14: =SUM(C14:N14) -> 0
B15: ='Property Management Overview'!B15 -> INTERIOR MAINTENANCE | C15: 0 | D15: 0 | E15: 0 | F15: 0 | G15: 0 | H15: 0 | I15: 0 | J15: 0 | K15: 0 | L15: 0 | M15: 0 | N15: 0 | O15: =SUM(C15:N15) -> 0
B16: ='Property Management Overview'!B16 -> INTERIOR REPAIRS | C16: 0 | D16: 0 | E16: 0 | F16: 0 | G16: 0 | H16: 0 | I16: 0 | J16: 0 | K16: 0 | L16: 0 | M16: 0 | N16: 0 | O16: =SUM(C16:N16) -> 0
B17: ='Property Management Overview'!B17 -> HOUSEKEEPING | C17: 0 | D17: 0 | E17: 0 | F17: 0 | G17: 0 | H17: 0 | I17: 0 | J17: 0 | K17: 0 | L17: 0 | M17: 0 | N17: 0 | O17: =SUM(C17:N17) -> 0
B18: ='Property Management Overview'!B18 -> EXTERIOR MAINTENANCE | C18: 0 | D18: 0 | E18: 0 | F18: 0 | G18: 0 | H18: 0 | I18: 0 | J18: 0 | K18: 0 | L18: 0 | M18: 0 | N18: 0 | O18: =SUM(C18:N18) -> 0
B19: ='Property Management Overview'!B19 -> EXTERIOR REPAIRS | C19: 0 | D19: 0 | E19: 0 | F19: 0 | G19: 0 | H19: 0 | I19: 0 | J19: 0 | K19: 0 | L19: 0 | M19: 0 | N19: 0 | O19: =SUM(C19:N19) -> 0
B20: ='Property Management Overview'!B20 -> GROUNDSKEEPING | C20: 0 | D20: 0 | E20: 0 | F20: 0 | G20: 0 | H20: 0 | I20: 0 | J20: 0 | K20: 0 | L20: 0 | M20: 0 | N20: 0 | O20: =SUM(C20:N20) -> 0
B21: ='Property Management Overview'!B14 -> AIR+LISTRIK | O21: =SUM(C21:N21) -> 0
B22: ='Property Management Overview'!B22 -> GAS | C22: 0 | D22: 0 | E22: 0 | F22: 0 | G22: 0 | H22: 0 | I22: 0 | J22: 0 | K22: 0 | L22: 0 | M22: 0 | N22: 0 | O22: =SUM(C22:N22) -> 0
B23: =#REF! -> #REF! | C23: 0 | D23: 0 | E23: 0 | F23: 0 | G23: 0 | H23: 0 | I23: 0 | J23: 0 | K23: 0 | L23: 0 | M23: 0 | N23: 0 | O23: =SUM(C23:N23) -> 0
B24: ='Property Management Overview'!B24 -> SEWAGE | C24: 0 | D24: 0 | E24: 0 | F24: 0 | G24: 0 | H24: 0 | I24: 0 | J24: 0 | K24: 0 | L24: 0 | M24: 0 | N24: 0 | O24: =SUM(C24:N24) -> 0
B25: ='Property Management Overview'!B25 -> REFUSE | C25: 0 | D25: 0 | E25: 0 | F25: 0 | G25: 0 | H25: 0 | I25: 0 | J25: 0 | K25: 0 | L25: 0 | M25: 0 | N25: 0 | O25: =SUM(C25:N25) -> 0
B26: ='Property Management Overview'!B26 -> CORRESPONDENCE - Postage, Stationery, Phone, Etc. | C26: 0 | D26: 0 | E26: 0 | F26: 0 | G26: 0 | H26: 0 | I26: 0 | J26: 0 | K26: 0 | L26: 0 | M26: 0 | N26: 0 | O26: =SUM(C26:N26) -> 0
B27: ='Property Management Overview'!B27 -> CARETAKER FEES / SALARY | C27: 0 | D27: 0 | E27: 0 | F27: 0 | G27: 0 | H27: 0 | I27: 0 | J27: 0 | K27: 0 | L27: 0 | M27: 0 | N27: 0 | O27: =SUM(C27:N27) -> 0
B28: ='Property Management Overview'!B28 -> TRAVEL EXPENSES | C28: 0 | D28: 0 | E28: 0 | F28: 0 | G28: 0 | H28: 0 | I28: 0 | J28: 0 | K28: 0 | L28: 0 | M28: 0 | N28: 0 | O28: =SUM(C28:N28) -> 0
B29: ='Property Management Overview'!B29 -> EQUIPMENT / APPLIANCE PURCHASES | C29: 0 | D29: 0 | E29: 0 | F29: 0 | G29: 0 | H29: 0 | I29: 0 | J29: 0 | K29: 0 | L29: 0 | M29: 0 | N29: 0 | O29: =SUM(C29:N29) -> 0
B30: ='Property Management Overview'!B30 -> EQUIPMENT / APPLIANCE RENTAL FEES | C30: 0 | D30: 0 | E30: 0 | F30: 0 | G30: 0 | H30: 0 | I30: 0 | J30: 0 | K30: 0 | L30: 0 | M30: 0 | N30: 0 | O30: =SUM(C30:N30) -> 0
B31: ='Property Management Overview'!B31 -> LAND TAX | C31: 0 | D31: 0 | E31: 0 | F31: 0 | G31: 188577 | H31: 0 | I31: 0 | J31: 0 | K31: 0 | L31: 0 | M31: 0 | N31: 0 | O31: =SUM(C31:N31) -> 188577
B32: ='Property Management Overview'!B32 -> BORROWING EXPENSES | C32: 0 | D32: 0 | E32: 0 | F32: 0 | G32: 0 | H32: 0 | I32: 0 | J32: 0 | K32: 0 | L32: 0 | M32: 0 | N32: 0 | O32: =SUM(C32:N32) -> 0
B33: ='Property Management Overview'!B33 -> LOAN(S) INTEREST | C33: 0 | D33: 0 | E33: 0 | F33: 0 | G33: 0 | H33: 0 | I33: 0 | J33: 0 | K33: 0 | L33: 0 | M33: 0 | N33: 0 | O33: =SUM(C33:N33) -> 0
B34: ='Property Management Overview'!B34 -> TRAVEL EXPENSES | C34: 0 | D34: 0 | E34: 0 | F34: 0 | G34: 0 | H34: 0 | I34: 0 | J34: 0 | K34: 0 | L34: 0 | M34: 0 | N34: 0 | O34: =SUM(C34:N34) -> 0
B35: ='Property Management Overview'!B35 -> OTHER | C35: 0 | D35: 0 | E35: 0 | F35: 0 | G35: 0 | H35: 0 | I35: 0 | J35: 0 | K35: 0 | L35: 0 | M35: 0 | N35: 0 | O35: =SUM(C35:N35) -> 0
... B42: ='Property Management Overview'!B42 -> OTHER | C42: 0 | D42: 0 | E42: 0 | F42: 0 | G42: 0 | H42: 0 | I42: 0 | J42: 0 | K42: 0 | L42: 0 | M42: 0 | N42: 0 | O42: =SUM(C42:N42) -> 0
B43: TOTAL EXPENSES | C43: =SUM(C11:C42) -> 100000 | D43: =SUM(D11:D42) -> 100000 | E43: =SUM(E11:E42) -> 0 | F43: =SUM(F11:F42) -> 0 | G43: =SUM(G11:G42) -> 188577 | H43: =SUM(H11:H42) -> 0 | I43: =SUM(I11:I42) -> 0 | J43: =SUM(J11:J42) -> 0 | ... N43: =SUM(N11:N42) -> 0 | O43: =SUM(C43:N43) -> 388577
B45: YEAR-TO-DATE INCOME LESS EXPENSES | C45: =C7-C43 -> 900000 | D45: =D7-D43 -> 900000 | E45: =E7-E43 -> 0 | F45: =F7-F43 -> 0 | G45: =G7-G43 -> -188577 | H45: =H7-H43 -> 0 | I45: =I7-I43 -> 0 | J45: =J7-J43 -> 0 | ... O45: =O7-O43 -> 1611423

Sheet Property 6
B1: PROPERTY MANAGEMENT SPREADSHEET TEMPLATE
B2: PROPERTY 6 ADDRESS | C2: 123 Main Street, City, State 10001
B3: INCOME | C3: JAN | D3: FEB | E3: MAR | F3: APR | G3: MAY | H3: JUN | I3: JUL | J3: AUG | K3: SEPT | L3: OCT | M3: NOV | N3: DEC | O3: YR TOTAL
B4: MULTI-PROPERTY INCOME OVERVIEW
B5: ='Property Management Overview'!B5 -> RENTAL INCOME | C5: 0 | D5: 0 | E5: 0 | F5: 0 | G5: 0 | H5: 0 | I5: 0 | J5: 0 | K5: 0 | L5: 0 | M5: 0 | N5: 0 | O5: =SUM(C5:N5) -> 0
B6: ='Property Management Overview'!B6 -> OTHER RENTAL INCOME – Late Fees, Etc. | C6: 0 | D6: 0 | E6: 0 | F6: 0 | G6: 0 | H6: 0 | I6: 0 | J6: 0 | K6: 0 | L6: 0 | M6: 0 | N6: 0 | O6: =SUM(C6:N6) -> 0
B7: GROSS RENTAL INCOME | C7: =SUM(C5:C6) -> 0 | D7: =SUM(D5:D6) -> 0 | E7: =SUM(E5:E6) -> 0 | F7: =SUM(F5:F6) -> 0 | G7: =SUM(G5:G6) -> 0 | H7: =SUM(H5:H6) -> 0 | I7: =SUM(I5:I6) -> 0 | J7: =SUM(J5:J6) -> 0 | ... N7: =SUM(N5:N6) -> 0 | O7: =SUM(C7:N7) -> 0
B9: EXPENSES | C9: JAN | D9: FEB | E9: MAR | F9: APR | G9: MAY | H9: JUN | I9: JUL | J9: AUG | K9: SEPT | L9: OCT | M9: NOV | N9: DEC | O9: YR TOTAL
B10: ='Property Management Overview'!B10 -> MULTI-PROPERTY EXPENSES OVERVIEW
B11: ='Property Management Overview'!B11 -> MARKETING / ADVERTISING | C11: 0 | D11: 0 | E11: 0 | F11: 0 | G11: 0 | H11: 0 | I11: 0 | J11: 0 | K11: 0 | L11: 0 | M11: 0 | N11: 0 | O11: =SUM(C11:N11) -> 0
B12: ='Property Management Overview'!B12 -> SERVICE CHARGE | C12: 0 | D12: 0 | E12: 0 | F12: 0 | G12: 0 | H12: 0 | I12: 0 | J12: 0 | K12: 0 | L12: 0 | M12: 0 | N12: 0 | O12: =SUM(C12:N12) -> 0
B13: ='Property Management Overview'!B13 -> AGENT FEES / COMMISSIONS | C13: 0 | D13: 0 | E13: 0 | F13: 0 | G13: 0 | H13: 0 | I13: 0 | J13: 0 | K13: 0 | L13: 0 | M13: 0 | N13: 0 | O13: =SUM(C13:N13) -> 0
B14: ='Property Management Overview'!B23 -> INSURANCE | C14: 0 | D14: 0 | E14: 0 | F14: 0 | G14: 0 | H14: 0 | I14: 0 | J14: 0 | K14: 0 | L14: 0 | M14: 0 | N14: 0 | O14: =SUM(C14:N14) -> 0
B15: ='Property Management Overview'!B15 -> INTERIOR MAINTENANCE | C15: 0 | D15: 0 | E15: 0 | F15: 0 | G15: 0 | H15: 0 | I15: 0 | J15: 0 | K15: 0 | L15: 0 | M15: 0 | N15: 0 | O15: =SUM(C15:N15) -> 0
B16: ='Property Management Overview'!B16 -> INTERIOR REPAIRS | C16: 0 | D16: 0 | E16: 0 | F16: 0 | G16: 0 | H16: 0 | I16: 0 | J16: 0 | K16: 0 | L16: 0 | M16: 0 | N16: 0 | O16: =SUM(C16:N16) -> 0
B17: ='Property Management Overview'!B17 -> HOUSEKEEPING | C17: 0 | D17: 0 | E17: 0 | F17: 0 | G17: 0 | H17: 0 | I17: 0 | J17: 0 | K17: 0 | L17: 0 | M17: 0 | N17: 0 | O17: =SUM(C17:N17) -> 0
B18: ='Property Management Overview'!B18 -> EXTERIOR MAINTENANCE | C18: 0 | D18: 0 | E18: 0 | F18: 0 | G18: 0 | H18: 0 | I18: 0 | J18: 0 | K18: 0 | L18: 0 | M18: 0 | N18: 0 | O18: =SUM(C18:N18) -> 0
B19: ='Property Management Overview'!B19 -> EXTERIOR REPAIRS | C19: 0 | D19: 0 | E19: 0 | F19: 0 | G19: 0 | H19: 0 | I19: 0 | J19: 0 | K19: 0 | L19: 0 | M19: 0 | N19: 0 | O19: =SUM(C19:N19) -> 0
B20: ='Property Management Overview'!B20 -> GROUNDSKEEPING | C20: 0 | D20: 0 | E20: 0 | F20: 0 | G20: 0 | H20: 0 | I20: 0 | J20: 0 | K20: 0 | L20: 0 | M20: 0 | N20: 0 | O20: =SUM(C20:N20) -> 0
B21: ='Property Management Overview'!B14 -> AIR+LISTRIK | C21: 0 | D21: 0 | E21: 0 | F21: 0 | G21: 0 | H21: 0 | I21: 0 | J21: 0 | K21: 0 | L21: 0 | M21: 0 | N21: 0 | O21: =SUM(C21:N21) -> 0
B22: ='Property Management Overview'!B22 -> GAS | C22: 0 | D22: 0 | E22: 0 | F22: 0 | G22: 0 | H22: 0 | I22: 0 | J22: 0 | K22: 0 | L22: 0 | M22: 0 | N22: 0 | O22: =SUM(C22:N22) -> 0
B23: =#REF! -> #REF! | C23: 0 | D23: 0 | E23: 0 | F23: 0 | G23: 0 | H23: 0 | I23: 0 | J23: 0 | K23: 0 | L23: 0 | M23: 0 | N23: 0 | O23: =SUM(C23:N23) -> 0
B24: ='Property Management Overview'!B24 -> SEWAGE | C24: 0 | D24: 0 | E24: 0 | F24: 0 | G24: 0 | H24: 0 | I24: 0 | J24: 0 | K24: 0 | L24: 0 | M24: 0 | N24: 0 | O24: =SUM(C24:N24) -> 0
B25: ='Property Management Overview'!B25 -> REFUSE | C25: 0 | D25: 0 | E25: 0 | F25: 0 | G25: 0 | H25: 0 | I25: 0 | J25: 0 | K25: 0 | L25: 0 | M25: 0 | N25: 0 | O25: =SUM(C25:N25) -> 0
B26: ='Property Management Overview'!B26 -> CORRESPONDENCE - Postage, Stationery, Phone, Etc. | C26: 0 | D26: 0 | E26: 0 | F26: 0 | G26: 0 | H26: 0 | I26: 0 | J26: 0 | K26: 0 | L26: 0 | M26: 0 | N26: 0 | O26: =SUM(C26:N26) -> 0
B27: ='Property Management Overview'!B27 -> CARETAKER FEES / SALARY | C27: 0 | D27: 0 | E27: 0 | F27: 0 | G27: 0 | H27: 0 | I27: 0 | J27: 0 | K27: 0 | L27: 0 | M27: 0 | N27: 0 | O27: =SUM(C27:N27) -> 0
B28: ='Property Management Overview'!B28 -> TRAVEL EXPENSES | C28: 0 | D28: 0 | E28: 0 | F28: 0 | G28: 0 | H28: 0 | I28: 0 | J28: 0 | K28: 0 | L28: 0 | M28: 0 | N28: 0 | O28: =SUM(C28:N28) -> 0
B29: ='Property Management Overview'!B29 -> EQUIPMENT / APPLIANCE PURCHASES | C29: 0 | D29: 0 | E29: 0 | F29: 0 | G29: 0 | H29: 0 | I29: 0 | J29: 0 | K29: 0 | L29: 0 | M29: 0 | N29: 0 | O29: =SUM(C29:N29) -> 0
B30: ='Property Management Overview'!B30 -> EQUIPMENT / APPLIANCE RENTAL FEES | C30: 0 | D30: 0 | E30: 0 | F30: 0 | G30: 0 | H30: 0 | I30: 0 | J30: 0 | K30: 0 | L30: 0 | M30: 0 | N30: 0 | O30: =SUM(C30:N30) -> 0
B31: ='Property Management Overview'!B31 -> LAND TAX | C31: 0 | D31: 0 | E31: 0 | F31: 0 | G31: 0 | H31: 0 | I31: 0 | J31: 0 | K31: 0 | L31: 0 | M31: 0 | N31: 0 | O31: =SUM(C31:N31) -> 0
B32: ='Property Management Overview'!B32 -> BORROWING EXPENSES | C32: 0 | D32: 0 | E32: 0 | F32: 0 | G32: 0 | H32: 0 | I32: 0 | J32: 0 | K32: 0 | L32: 0 | M32: 0 | N32: 0 | O32: =SUM(C32:N32) -> 0
B33: ='Property Management Overview'!B33 -> LOAN(S) INTEREST | C33: 0 | D33: 0 | E33: 0 | F33: 0 | G33: 0 | H33: 0 | I33: 0 | J33: 0 | K33: 0 | L33: 0 | M33: 0 | N33: 0 | O33: =SUM(C33:N33) -> 0
B34: ='Property Management Overview'!B34 -> TRAVEL EXPENSES | C34: 0 | D34: 0 | E34: 0 | F34: 0 | G34: 0 | H34: 0 | I34: 0 | J34: 0 | K34: 0 | L34: 0 | M34: 0 | N34: 0 | O34: =SUM(C34:N34) -> 0
B35: ='Property Management Overview'!B35 -> OTHER | C35: 0 | D35: 0 | E35: 0 | F35: 0 | G35: 0 | H35: 0 | I35: 0 | J35: 0 | K35: 0 | L35: 0 | M35: 0 | N35: 0 | O35: =SUM(C35:N35) -> 0
... B42: ='Property Management Overview'!B42 -> OTHER | C42: 0 | D42: 0 | E42: 0 | F42: 0 | G42: 0 | H42: 0 | I42: 0 | J42: 0 | K42: 0 | L42: 0 | M42: 0 | N42: 0 | O42: =SUM(C42:N42) -> 0
B43: TOTAL EXPENSES | C43: =SUM(C11:C42) -> 0 | D43: =SUM(D11:D42) -> 0 | E43: =SUM(E11:E42) -> 0 | F43: =SUM(F11:F42) -> 0 | G43: =SUM(G11:G42) -> 0 | H43: =SUM(H11:H42) -> 0 | I43: =SUM(I11:I42) -> 0 | J43: =SUM(J11:J42) -> 0 | ... N43: =SUM(N11:N42) -> 0 | O43: =SUM(C43:N43) -> 0
B45: YEAR-TO-DATE INCOME LESS EXPENSES | C45: =C7-C43 -> 0 | D45: =D7-D43 -> 0 | E45: =E7-E43 -> 0 | F45: =F7-F43 -> 0 | G45: =G7-G43 -> 0 | H45: =H7-H43 -> 0 | I45: =I7-I43 -> 0 | J45: =J7-J43 -> 0 | ... O45: =O7-O43 -> 0

Sheet Property 7
B1: PROPERTY MANAGEMENT SPREADSHEET TEMPLATE
B2: PROPERTY 7 ADDRESS | C2: 123 Main Street, City, State 10001
B3: INCOME | C3: JAN | D3: FEB | E3: MAR | F3: APR | G3: MAY | H3: JUN | I3: JUL | J3: AUG | K3: SEPT | L3: OCT | M3: NOV | N3: DEC | O3: YR TOTAL
B4: MULTI-PROPERTY INCOME OVERVIEW
B5: ='Property Management Overview'!B5 -> RENTAL INCOME | C5: 0 | D5: 0 | E5: 0 | F5: 0 | G5: 0 | H5: 0 | I5: 0 | J5: 0 | K5: 0 | L5: 0 | M5: 0 | N5: 0 | O5: =SUM(C5:N5) -> 0
B6: ='Property Management Overview'!B6 -> OTHER RENTAL INCOME – Late Fees, Etc. | C6: 0 | D6: 0 | E6: 0 | F6: 0 | G6: 0 | H6: 0 | I6: 0 | J6: 0 | K6: 0 | L6: 0 | M6: 0 | N6: 0 | O6: =SUM(C6:N6) -> 0
B7: GROSS RENTAL INCOME | C7: =SUM(C5:C6) -> 0 | D7: =SUM(D5:D6) -> 0 | E7: =SUM(E5:E6) -> 0 | F7: =SUM(F5:F6) -> 0 | G7: =SUM(G5:G6) -> 0 | H7: =SUM(H5:H6) -> 0 | I7: =SUM(I5:I6) -> 0 | J7: =SUM(J5:J6) -> 0 | ... N7: =SUM(N5:N6) -> 0 | O7: =SUM(C7:N7) -> 0
B9: EXPENSES | C9: JAN | D9: FEB | E9: MAR | F9: APR | G9: MAY | H9: JUN | I9: JUL | J9: AUG | K9: SEPT | L9: OCT | M9: NOV | N9: DEC | O9: YR TOTAL
B10: ='Property Management Overview'!B10 -> MULTI-PROPERTY EXPENSES OVERVIEW
B11: ='Property Management Overview'!B11 -> MARKETING / ADVERTISING | C11: 0 | D11: 0 | E11: 0 | F11: 0 | G11: 0 | H11: 0 | I11: 0 | J11: 0 | K11: 0 | L11: 0 | M11: 0 | N11: 0 | O11: =SUM(C11:N11) -> 0
B12: ='Property Management Overview'!B12 -> SERVICE CHARGE | C12: 0 | D12: 0 | E12: 0 | F12: 0 | G12: 0 | H12: 0 | I12: 0 | J12: 0 | K12: 0 | L12: 0 | M12: 0 | N12: 0 | O12: =SUM(C12:N12) -> 0
B13: ='Property Management Overview'!B13 -> AGENT FEES / COMMISSIONS | C13: 0 | D13: 0 | E13: 0 | F13: 0 | G13: 0 | H13: 0 | I13: 0 | J13: 0 | K13: 0 | L13: 0 | M13: 0 | N13: 0 | O13: =SUM(C13:N13) -> 0
B14: ='Property Management Overview'!B23 -> INSURANCE | C14: 0 | D14: 0 | E14: 0 | F14: 0 | G14: 0 | H14: 0 | I14: 0 | J14: 0 | K14: 0 | L14: 0 | M14: 0 | N14: 0 | O14: =SUM(C14:N14) -> 0
B15: ='Property Management Overview'!B15 -> INTERIOR MAINTENANCE | C15: 0 | D15: 0 | E15: 0 | F15: 0 | G15: 0 | H15: 0 | I15: 0 | J15: 0 | K15: 0 | L15: 0 | M15: 0 | N15: 0 | O15: =SUM(C15:N15) -> 0
B16: ='Property Management Overview'!B16 -> INTERIOR REPAIRS | C16: 0 | D16: 0 | E16: 0 | F16: 0 | G16: 0 | H16: 0 | I16: 0 | J16: 0 | K16: 0 | L16: 0 | M16: 0 | N16: 0 | O16: =SUM(C16:N16) -> 0
B17: ='Property Management Overview'!B17 -> HOUSEKEEPING | C17: 0 | D17: 0 | E17: 0 | F17: 0 | G17: 0 | H17: 0 | I17: 0 | J17: 0 | K17: 0 | L17: 0 | M17: 0 | N17: 0 | O17: =SUM(C17:N17) -> 0
B18: ='Property Management Overview'!B18 -> EXTERIOR MAINTENANCE | C18: 0 | D18: 0 | E18: 0 | F18: 0 | G18: 0 | H18: 0 | I18: 0 | J18: 0 | K18: 0 | L18: 0 | M18: 0 | N18: 0 | O18: =SUM(C18:N18) -> 0
B19: ='Property Management Overview'!B19 -> EXTERIOR REPAIRS | C19: 0 | D19: 0 | E19: 0 | F19: 0 | G19: 0 | H19: 0 | I19: 0 | J19: 0 | K19: 0 | L19: 0 | M19: 0 | N19: 0 | O19: =SUM(C19:N19) -> 0
B20: ='Property Management Overview'!B20 -> GROUNDSKEEPING | C20: 0 | D20: 0 | E20: 0 | F20: 0 | G20: 0 | H20: 0 | I20: 0 | J20: 0 | K20: 0 | L20: 0 | M20: 0 | N20: 0 | O20: =SUM(C20:N20) -> 0
B21: ='Property Management Overview'!B14 -> AIR+LISTRIK | C21: 0 | D21: 0 | E21: 0 | F21: 0 | G21: 0 | H21: 0 | I21: 0 | J21: 0 | K21: 0 | L21: 0 | M21: 0 | N21: 0 | O21: =SUM(C21:N21) -> 0
B22: ='Property Management Overview'!B22 -> GAS | C22: 0 | D22: 0 | E22: 0 | F22: 0 | G22: 0 | H22: 0 | I22: 0 | J22: 0 | K22: 0 | L22: 0 | M22: 0 | N22: 0 | O22: =SUM(C22:N22) -> 0
B23: =#REF! -> #REF! | C23: 0 | D23: 0 | E23: 0 | F23: 0 | G23: 0 | H23: 0 | I23: 0 | J23: 0 | K23: 0 | L23: 0 | M23: 0 | N23: 0 | O23: =SUM(C23:N23) -> 0
B24: ='Property Management Overview'!B24 -> SEWAGE | C24: 0 | D24: 0 | E24: 0 | F24: 0 | G24: 0 | H24: 0 | I24: 0 | J24: 0 | K24: 0 | L24: 0 | M24: 0 | N24: 0 | O24: =SUM(C24:N24) -> 0
B25: ='Property Management Overview'!B25 -> REFUSE | C25: 0 | D25: 0 | E25: 0 | F25: 0 | G25: 0 | H25: 0 | I25: 0 | J25: 0 | K25: 0 | L25: 0 | M25: 0 | N25: 0 | O25: =SUM(C25:N25) -> 0
B26: ='Property Management Overview'!B26 -> CORRESPONDENCE - Postage, Stationery, Phone, Etc. | C26: 0 | D26: 0 | E26: 0 | F26: 0 | G26: 0 | H26: 0 | I26: 0 | J26: 0 | K26: 0 | L26: 0 | M26: 0 | N26: 0 | O26: =SUM(C26:N26) -> 0
B27: ='Property Management Overview'!B27 -> CARETAKER FEES / SALARY | C27: 0 | D27: 0 | E27: 0 | F27: 0 | G27: 0 | H27: 0 | I27: 0 | J27: 0 | K27: 0 | L27: 0 | M27: 0 | N27: 0 | O27: =SUM(C27:N27) -> 0
B28: ='Property Management Overview'!B28 -> TRAVEL EXPENSES | C28: 0 | D28: 0 | E28: 0 | F28: 0 | G28: 0 | H28: 0 | I28: 0 | J28: 0 | K28: 0 | L28: 0 | M28: 0 | N28: 0 | O28: =SUM(C28:N28) -> 0
B29: ='Property Management Overview'!B29 -> EQUIPMENT / APPLIANCE PURCHASES | C29: 0 | D29: 0 | E29: 0 | F29: 0 | G29: 0 | H29: 0 | I29: 0 | J29: 0 | K29: 0 | L29: 0 | M29: 0 | N29: 0 | O29: =SUM(C29:N29) -> 0
B30: ='Property Management Overview'!B30 -> EQUIPMENT / APPLIANCE RENTAL FEES | C30: 0 | D30: 0 | E30: 0 | F30: 0 | G30: 0 | H30: 0 | I30: 0 | J30: 0 | K30: 0 | L30: 0 | M30: 0 | N30: 0 | O30: =SUM(C30:N30) -> 0
B31: ='Property Management Overview'!B31 -> LAND TAX | C31: 0 | D31: 0 | E31: 0 | F31: 0 | G31: 0 | H31: 0 | I31: 0 | J31: 0 | K31: 0 | L31: 0 | M31: 0 | N31: 0 | O31: =SUM(C31:N31) -> 0
B32: ='Property Management Overview'!B32 -> BORROWING EXPENSES | C32: 0 | D32: 0 | E32: 0 | F32: 0 | G32: 0 | H32: 0 | I32: 0 | J32: 0 | K32: 0 | L32: 0 | M32: 0 | N32: 0 | O32: =SUM(C32:N32) -> 0
B33: ='Property Management Overview'!B33 -> LOAN(S) INTEREST | C33: 0 | D33: 0 | E33: 0 | F33: 0 | G33: 0 | H33: 0 | I33: 0 | J33: 0 | K33: 0 | L33: 0 | M33: 0 | N33: 0 | O33: =SUM(C33:N33) -> 0
B34: ='Property Management Overview'!B34 -> TRAVEL EXPENSES | C34: 0 | D34: 0 | E34: 0 | F34: 0 | G34: 0 | H34: 0 | I34: 0 | J34: 0 | K34: 0 | L34: 0 | M34: 0 | N34: 0 | O34: =SUM(C34:N34) -> 0
B35: ='Property Management Overview'!B35 -> OTHER | C35: 0 | D35: 0 | E35: 0 | F35: 0 | G35: 0 | H35: 0 | I35: 0 | J35: 0 | K35: 0 | L35: 0 | M35: 0 | N35: 0 | O35: =SUM(C35:N35) -> 0
... B42: ='Property Management Overview'!B42 -> OTHER | C42: 0 | D42: 0 | E42: 0 | F42: 0 | G42: 0 | H42: 0 | I42: 0 | J42: 0 | K42: 0 | L42: 0 | M42: 0 | N42: 0 | O42: =SUM(C42:N42) -> 0
B43: TOTAL EXPENSES | C43: =SUM(C11:C42) -> 0 | D43: =SUM(D11:D42) -> 0 | E43: =SUM(E11:E42) -> 0 | F43: =SUM(F11:F42) -> 0 | G43: =SUM(G11:G42) -> 0 | H43: =SUM(H11:H42) -> 0 | I43: =SUM(I11:I42) -> 0 | J43: =SUM(J11:J42) -> 0 | ... N43: =SUM(N11:N42) -> 0 | O43: =SUM(C43:N43) -> 0
B45: YEAR-TO-DATE INCOME LESS EXPENSES | C45: =C7-C43 -> 0 | D45: =D7-D43 -> 0 | E45: =E7-E43 -> 0 | F45: =F7-F43 -> 0 | G45: =G7-G43 -> 0 | H45: =H7-H43 -> 0 | I45: =I7-I43 -> 0 | J45: =J7-J43 -> 0 | ... O45: =O7-O43 -> 0

Sheet Property 8
B1: PROPERTY MANAGEMENT SPREADSHEET TEMPLATE
B2: PROPERTY 8 ADDRESS | C2: 123 Main Street, City, State 10001
B3: INCOME | C3: JAN | D3: FEB | E3: MAR | F3: APR | G3: MAY | H3: JUN | I3: JUL | J3: AUG | K3: SEPT | L3: OCT | M3: NOV | N3: DEC | O3: YR TOTAL
B4: MULTI-PROPERTY INCOME OVERVIEW
B5: ='Property Management Overview'!B5 -> RENTAL INCOME | C5: 0 | D5: 0 | E5: 0 | F5: 0 | G5: 0 | H5: 0 | I5: 0 | J5: 0 | K5: 0 | L5: 0 | M5: 0 | N5: 0 | O5: =SUM(C5:N5) -> 0
B6: ='Property Management Overview'!B6 -> OTHER RENTAL INCOME – Late Fees, Etc. | C6: 0 | D6: 0 | E6: 0 | F6: 0 | G6: 0 | H6: 0 | I6: 0 | J6: 0 | K6: 0 | L6: 0 | M6: 0 | N6: 0 | O6: =SUM(C6:N6) -> 0
B7: GROSS RENTAL INCOME | C7: =SUM(C5:C6) -> 0 | D7: =SUM(D5:D6) -> 0 | E7: =SUM(E5:E6) -> 0 | F7: =SUM(F5:F6) -> 0 | G7: =SUM(G5:G6) -> 0 | H7: =SUM(H5:H6) -> 0 | I7: =SUM(I5:I6) -> 0 | J7: =SUM(J5:J6) -> 0 | ... N7: =SUM(N5:N6) -> 0 | O7: =SUM(C7:N7) -> 0
B9: EXPENSES | C9: JAN | D9: FEB | E9: MAR | F9: APR | G9: MAY | H9: JUN | I9: JUL | J9: AUG | K9: SEPT | L9: OCT | M9: NOV | N9: DEC | O9: YR TOTAL
B10: ='Property Management Overview'!B10 -> MULTI-PROPERTY EXPENSES OVERVIEW
B11: ='Property Management Overview'!B11 -> MARKETING / ADVERTISING | C11: 0 | D11: 0 | E11: 0 | F11: 0 | G11: 0 | H11: 0 | I11: 0 | J11: 0 | K11: 0 | L11: 0 | M11: 0 | N11: 0 | O11: =SUM(C11:N11) -> 0
B12: ='Property Management Overview'!B12 -> SERVICE CHARGE | C12: 0 | D12: 0 | E12: 0 | F12: 0 | G12: 0 | H12: 0 | I12: 0 | J12: 0 | K12: 0 | L12: 0 | M12: 0 | N12: 0 | O12: =SUM(C12:N12) -> 0
B13: ='Property Management Overview'!B13 -> AGENT FEES / COMMISSIONS | C13: 0 | D13: 0 | E13: 0 | F13: 0 | G13: 0 | H13: 0 | I13: 0 | J13: 0 | K13: 0 | L13: 0 | M13: 0 | N13: 0 | O13: =SUM(C13:N13) -> 0
B14: ='Property Management Overview'!B23 -> INSURANCE | C14: 0 | D14: 0 | E14: 0 | F14: 0 | G14: 0 | H14: 0 | I14: 0 | J14: 0 | K14: 0 | L14: 0 | M14: 0 | N14: 0 | O14: =SUM(C14:N14) -> 0
B15: ='Property Management Overview'!B15 -> INTERIOR MAINTENANCE | C15: 0 | D15: 0 | E15: 0 | F15: 0 | G15: 0 | H15: 0 | I15: 0 | J15: 0 | K15: 0 | L15: 0 | M15: 0 | N15: 0 | O15: =SUM(C15:N15) -> 0
B16: ='Property Management Overview'!B16 -> INTERIOR REPAIRS | C16: 0 | D16: 0 | E16: 0 | F16: 0 | G16: 0 | H16: 0 | I16: 0 | J16: 0 | K16: 0 | L16: 0 | M16: 0 | N16: 0 | O16: =SUM(C16:N16) -> 0
B17: ='Property Management Overview'!B17 -> HOUSEKEEPING | C17: 0 | D17: 0 | E17: 0 | F17: 0 | G17: 0 | H17: 0 | I17: 0 | J17: 0 | K17: 0 | L17: 0 | M17: 0 | N17: 0 | O17: =SUM(C17:N17) -> 0
B18: ='Property Management Overview'!B18 -> EXTERIOR MAINTENANCE | C18: 0 | D18: 0 | E18: 0 | F18: 0 | G18: 0 | H18: 0 | I18: 0 | J18: 0 | K18: 0 | L18: 0 | M18: 0 | N18: 0 | O18: =SUM(C18:N18) -> 0
B19: ='Property Management Overview'!B19 -> EXTERIOR REPAIRS | C19: 0 | D19: 0 | E19: 0 | F19: 0 | G19: 0 | H19: 0 | I19: 0 | J19: 0 | K19: 0 | L19: 0 | M19: 0 | N19: 0 | O19: =SUM(C19:N19) -> 0
B20: ='Property Management Overview'!B20 -> GROUNDSKEEPING | C20: 0 | D20: 0 | E20: 0 | F20: 0 | G20: 0 | H20: 0 | I20: 0 | J20: 0 | K20: 0 | L20: 0 | M20: 0 | N20: 0 | O20: =SUM(C20:N20) -> 0
B21: ='Property Management Overview'!B14 -> AIR+LISTRIK | C21: 0 | D21: 0 | E21: 0 | F21: 0 | G21: 0 | H21: 0 | I21: 0 | J21: 0 | K21: 0 | L21: 0 | M21: 0 | N21: 0 | O21: =SUM(C21:N21) -> 0
B22: ='Property Management Overview'!B22 -> GAS | C22: 0 | D22: 0 | E22: 0 | F22: 0 | G22: 0 | H22: 0 | I22: 0 | J22: 0 | K22: 0 | L22: 0 | M22: 0 | N22: 0 | O22: =SUM(C22:N22) -> 0
B23: =#REF! -> #REF! | C23: 0 | D23: 0 | E23: 0 | F23: 0 | G23: 0 | H23: 0 | I23: 0 | J23: 0 | K23: 0 | L23: 0 | M23: 0 | N23: 0 | O23: =SUM(C23:N23) -> 0
B24: ='Property Management Overview'!B24 -> SEWAGE | C24: 0 | D24: 0 | E24: 0 | F24: 0 | G24: 0 | H24: 0 | I24: 0 | J24: 0 | K24: 0 | L24: 0 | M24: 0 | N24: 0 | O24: =SUM(C24:N24) -> 0
B25: ='Property Management Overview'!B25 -> REFUSE | C25: 0 | D25: 0 | E25: 0 | F25: 0 | G25: 0 | H25: 0 | I25: 0 | J25: 0 | K25: 0 | L25: 0 | M25: 0 | N25: 0 | O25: =SUM(C25:N25) -> 0
B26: ='Property Management Overview'!B26 -> CORRESPONDENCE - Postage, Stationery, Phone, Etc. | C26: 0 | D26: 0 | E26: 0 | F26: 0 | G26: 0 | H26: 0 | I26: 0 | J26: 0 | K26: 0 | L26: 0 | M26: 0 | N26: 0 | O26: =SUM(C26:N26) -> 0
B27: ='Property Management Overview'!B27 -> CARETAKER FEES / SALARY | C27: 0 | D27: 0 | E27: 0 | F27: 0 | G27: 0 | H27: 0 | I27: 0 | J27: 0 | K27: 0 | L27: 0 | M27: 0 | N27: 0 | O27: =SUM(C27:N27) -> 0
B28: ='Property Management Overview'!B28 -> TRAVEL EXPENSES | C28: 0 | D28: 0 | E28: 0 | F28: 0 | G28: 0 | H28: 0 | I28: 0 | J28: 0 | K28: 0 | L28: 0 | M28: 0 | N28: 0 | O28: =SUM(C28:N28) -> 0
B29: ='Property Management Overview'!B29 -> EQUIPMENT / APPLIANCE PURCHASES | C29: 0 | D29: 0 | E29: 0 | F29: 0 | G29: 0 | H29: 0 | I29: 0 | J29: 0 | K29: 0 | L29: 0 | M29: 0 | N29: 0 | O29: =SUM(C29:N29) -> 0
B30: ='Property Management Overview'!B30 -> EQUIPMENT / APPLIANCE RENTAL FEES | C30: 0 | D30: 0 | E30: 0 | F30: 0 | G30: 0 | H30: 0 | I30: 0 | J30: 0 | K30: 0 | L30: 0 | M30: 0 | N30: 0 | O30: =SUM(C30:N30) -> 0
B31: ='Property Management Overview'!B31 -> LAND TAX | C31: 0 | D31: 0 | E31: 0 | F31: 0 | G31: 0 | H31: 0 | I31: 0 | J31: 0 | K31: 0 | L31: 0 | M31: 0 | N31: 0 | O31: =SUM(C31:N31) -> 0
B32: ='Property Management Overview'!B32 -> BORROWING EXPENSES | C32: 0 | D32: 0 | E32: 0 | F32: 0 | G32: 0 | H32: 0 | I32: 0 | J32: 0 | K32: 0 | L32: 0 | M32: 0 | N32: 0 | O32: =SUM(C32:N32) -> 0
B33: ='Property Management Overview'!B33 -> LOAN(S) INTEREST | C33: 0 | D33: 0 | E33: 0 | F33: 0 | G33: 0 | H33: 0 | I33: 0 | J33: 0 | K33: 0 | L33: 0 | M33: 0 | N33: 0 | O33: =SUM(C33:N33) -> 0
B34: ='Property Management Overview'!B34 -> TRAVEL EXPENSES | C34: 0 | D34: 0 | E34: 0 | F34: 0 | G34: 0 | H34: 0 | I34: 0 | J34: 0 | K34: 0 | L34: 0 | M34: 0 | N34: 0 | O34: =SUM(C34:N34) -> 0
B35: ='Property Management Overview'!B35 -> OTHER | C35: 0 | D35: 0 | E35: 0 | F35: 0 | G35: 0 | H35: 0 | I35: 0 | J35: 0 | K35: 0 | L35: 0 | M35: 0 | N35: 0 | O35: =SUM(C35:N35) -> 0
... B42: ='Property Management Overview'!B42 -> OTHER | C42: 0 | D42: 0 | E42: 0 | F42: 0 | G42: 0 | H42: 0 | I42: 0 | J42: 0 | K42: 0 | L42: 0 | M42: 0 | N42: 0 | O42: =SUM(C42:N42) -> 0
B43: TOTAL EXPENSES | C43: =SUM(C11:C42) -> 0 | D43: =SUM(D11:D42) -> 0 | E43: =SUM(E11:E42) -> 0 | F43: =SUM(F11:F42) -> 0 | G43: =SUM(G11:G42) -> 0 | H43: =SUM(H11:H42) -> 0 | I43: =SUM(I11:I42) -> 0 | J43: =SUM(J11:J42) -> 0 | ... N43: =SUM(N11:N42) -> 0 | O43: =SUM(C43:N43) -> 0
B45: YEAR-TO-DATE INCOME LESS EXPENSES | C45: =C7-C43 -> 0 | D45: =D7-D43 -> 0 | E45: =E7-E43 -> 0 | F45: =F7-F43 -> 0 | G45: =G7-G43 -> 0 | H45: =H7-H43 -> 0 | I45: =I7-I43 -> 0 | J45: =J7-J43 -> 0 | ... O45: =O7-O43 -> 0

Sheet Property 9
B1: PROPERTY MANAGEMENT SPREADSHEET TEMPLATE
B2: PROPERTY 9 ADDRESS | C2: 123 Main Street, City, State 10001
B3: INCOME | C3: JAN | D3: FEB | E3: MAR | F3: APR | G3: MAY | H3: JUN | I3: JUL | J3: AUG | K3: SEPT | L3: OCT | M3: NOV | N3: DEC | O3: YR TOTAL
B4: MULTI-PROPERTY INCOME OVERVIEW
B5: ='Property Management Overview'!B5 -> RENTAL INCOME | C5: 0 | D5: 0 | E5: 0 | F5: 0 | G5: 0 | H5: 0 | I5: 0 | J5: 0 | K5: 0 | L5: 0 | M5: 0 | N5: 0 | O5: =SUM(C5:N5) -> 0
B6: ='Property Management Overview'!B6 -> OTHER RENTAL INCOME – Late Fees, Etc. | C6: 0 | D6: 0 | E6: 0 | F6: 0 | G6: 0 | H6: 0 | I6: 0 | J6: 0 | K6: 0 | L6: 0 | M6: 0 | N6: 0 | O6: =SUM(C6:N6) -> 0
B7: GROSS RENTAL INCOME | C7: =SUM(C5:C6) -> 0 | D7: =SUM(D5:D6) -> 0 | E7: =SUM(E5:E6) -> 0 | F7: =SUM(F5:F6) -> 0 | G7: =SUM(G5:G6) -> 0 | H7: =SUM(H5:H6) -> 0 | I7: =SUM(I5:I6) -> 0 | J7: =SUM(J5:J6) -> 0 | ... N7: =SUM(N5:N6) -> 0 | O7: =SUM(C7:N7) -> 0
B9: EXPENSES | C9: JAN | D9: FEB | E9: MAR | F9: APR | G9: MAY | H9: JUN | I9: JUL | J9: AUG | K9: SEPT | L9: OCT | M9: NOV | N9: DEC | O9: YR TOTAL
B10: ='Property Management Overview'!B10 -> MULTI-PROPERTY EXPENSES OVERVIEW
B11: ='Property Management Overview'!B11 -> MARKETING / ADVERTISING | C11: 0 | D11: 0 | E11: 0 | F11: 0 | G11: 0 | H11: 0 | I11: 0 | J11: 0 | K11: 0 | L11: 0 | M11: 0 | N11: 0 | O11: =SUM(C11:N11) -> 0
B12: ='Property Management Overview'!B12 -> SERVICE CHARGE | C12: 0 | D12: 0 | E12: 0 | F12: 0 | G12: 0 | H12: 0 | I12: 0 | J12: 0 | K12: 0 | L12: 0 | M12: 0 | N12: 0 | O12: =SUM(C12:N12) -> 0
B13: ='Property Management Overview'!B13 -> AGENT FEES / COMMISSIONS | C13: 0 | D13: 0 | E13: 0 | F13: 0 | G13: 0 | H13: 0 | I13: 0 | J13: 0 | K13: 0 | L13: 0 | M13: 0 | N13: 0 | O13: =SUM(C13:N13) -> 0
B14: ='Property Management Overview'!B23 -> INSURANCE | C14: 0 | D14: 0 | E14: 0 | F14: 0 | G14: 0 | H14: 0 | I14: 0 | J14: 0 | K14: 0 | L14: 0 | M14: 0 | N14: 0 | O14: =SUM(C14:N14) -> 0
B15: ='Property Management Overview'!B15 -> INTERIOR MAINTENANCE | C15: 0 | D15: 0 | E15: 0 | F15: 0 | G15: 0 | H15: 0 | I15: 0 | J15: 0 | K15: 0 | L15: 0 | M15: 0 | N15: 0 | O15: =SUM(C15:N15) -> 0
B16: ='Property Management Overview'!B16 -> INTERIOR REPAIRS | C16: 0 | D16: 0 | E16: 0 | F16: 0 | G16: 0 | H16: 0 | I16: 0 | J16: 0 | K16: 0 | L16: 0 | M16: 0 | N16: 0 | O16: =SUM(C16:N16) -> 0
B17: ='Property Management Overview'!B17 -> HOUSEKEEPING | C17: 0 | D17: 0 | E17: 0 | F17: 0 | G17: 0 | H17: 0 | I17: 0 | J17: 0 | K17: 0 | L17: 0 | M17: 0 | N17: 0 | O17: =SUM(C17:N17) -> 0
B18: ='Property Management Overview'!B18 -> EXTERIOR MAINTENANCE | C18: 0 | D18: 0 | E18: 0 | F18: 0 | G18: 0 | H18: 0 | I18: 0 | J18: 0 | K18: 0 | L18: 0 | M18: 0 | N18: 0 | O18: =SUM(C18:N18) -> 0
B19: ='Property Management Overview'!B19 -> EXTERIOR REPAIRS | C19: 0 | D19: 0 | E19: 0 | F19: 0 | G19: 0 | H19: 0 | I19: 0 | J19: 0 | K19: 0 | L19: 0 | M19: 0 | N19: 0 | O19: =SUM(C19:N19) -> 0
B20: ='Property Management Overview'!B20 -> GROUNDSKEEPING | C20: 0 | D20: 0 | E20: 0 | F20: 0 | G20: 0 | H20: 0 | I20: 0 | J20: 0 | K20: 0 | L20: 0 | M20: 0 | N20: 0 | O20: =SUM(C20:N20) -> 0
B21: ='Property Management Overview'!B14 -> AIR+LISTRIK | C21: 0 | D21: 0 | E21: 0 | F21: 0 | G21: 0 | H21: 0 | I21: 0 | J21: 0 | K21: 0 | L21: 0 | M21: 0 | N21: 0 | O21: =SUM(C21:N21) -> 0
B22: ='Property Management Overview'!B22 -> GAS | C22: 0 | D22: 0 | E22: 0 | F22: 0 | G22: 0 | H22: 0 | I22: 0 | J22: 0 | K22: 0 | L22: 0 | M22: 0 | N22: 0 | O22: =SUM(C22:N22) -> 0
B23: =#REF! -> #REF! | C23: 0 | D23: 0 | E23: 0 | F23: 0 | G23: 0 | H23: 0 | I23: 0 | J23: 0 | K23: 0 | L23: 0 | M23: 0 | N23: 0 | O23: =SUM(C23:N23) -> 0
B24: ='Property Management Overview'!B24 -> SEWAGE | C24: 0 | D24: 0 | E24: 0 | F24: 0 | G24: 0 | H24: 0 | I24: 0 | J24: 0 | K24: 0 | L24: 0 | M24: 0 | N24: 0 | O24: =SUM(C24:N24) -> 0
B25: ='Property Management Overview'!B25 -> REFUSE | C25: 0 | D25: 0 | E25: 0 | F25: 0 | G25: 0 | H25: 0 | I25: 0 | J25: 0 | K25: 0 | L25: 0 | M25: 0 | N25: 0 | O25: =SUM(C25:N25) -> 0
B26: ='Property Management Overview'!B26 -> CORRESPONDENCE - Postage, Stationery, Phone, Etc. | C26: 0 | D26: 0 | E26: 0 | F26: 0 | G26: 0 | H26: 0 | I26: 0 | J26: 0 | K26: 0 | L26: 0 | M26: 0 | N26: 0 | O26: =SUM(C26:N26) -> 0
B27: ='Property Management Overview'!B27 -> CARETAKER FEES / SALARY | C27: 0 | D27: 0 | E27: 0 | F27: 0 | G27: 0 | H27: 0 | I27: 0 | J27: 0 | K27: 0 | L27: 0 | M27: 0 | N27: 0 | O27: =SUM(C27:N27) -> 0
B28: ='Property Management Overview'!B28 -> TRAVEL EXPENSES | C28: 0 | D28: 0 | E28: 0 | F28: 0 | G28: 0 | H28: 0 | I28: 0 | J28: 0 | K28: 0 | L28: 0 | M28: 0 | N28: 0 | O28: =SUM(C28:N28) -> 0
B29: ='Property Management Overview'!B29 -> EQUIPMENT / APPLIANCE PURCHASES | C29: 0 | D29: 0 | E29: 0 | F29: 0 | G29: 0 | H29: 0 | I29: 0 | J29: 0 | K29: 0 | L29: 0 | M29: 0 | N29: 0 | O29: =SUM(C29:N29) -> 0
B30: ='Property Management Overview'!B30 -> EQUIPMENT / APPLIANCE RENTAL FEES | C30: 0 | D30: 0 | E30: 0 | F30: 0 | G30: 0 | H30: 0 | I30: 0 | J30: 0 | K30: 0 | L30: 0 | M30: 0 | N30: 0 | O30: =SUM(C30:N30) -> 0
B31: ='Property Management Overview'!B31 -> LAND TAX | C31: 0 | D31: 0 | E31: 0 | F31: 0 | G31: 0 | H31: 0 | I31: 0 | J31: 0 | K31: 0 | L31: 0 | M31: 0 | N31: 0 | O31: =SUM(C31:N31) -> 0
B32: ='Property Management Overview'!B32 -> BORROWING EXPENSES | C32: 0 | D32: 0 | E32: 0 | F32: 0 | G32: 0 | H32: 0 | I32: 0 | J32: 0 | K32: 0 | L32: 0 | M32: 0 | N32: 0 | O32: =SUM(C32:N32) -> 0
B33: ='Property Management Overview'!B33 -> LOAN(S) INTEREST | C33: 0 | D33: 0 | E33: 0 | F33: 0 | G33: 0 | H33: 0 | I33: 0 | J33: 0 | K33: 0 | L33: 0 | M33: 0 | N33: 0 | O33: =SUM(C33:N33) -> 0
B34: ='Property Management Overview'!B34 -> TRAVEL EXPENSES | C34: 0 | D34: 0 | E34: 0 | F34: 0 | G34: 0 | H34: 0 | I34: 0 | J34: 0 | K34: 0 | L34: 0 | M34: 0 | N34: 0 | O34: =SUM(C34:N34) -> 0
B35: ='Property Management Overview'!B35 -> OTHER | C35: 0 | D35: 0 | E35: 0 | F35: 0 | G35: 0 | H35: 0 | I35: 0 | J35: 0 | K35: 0 | L35: 0 | M35: 0 | N35: 0 | O35: =SUM(C35:N35) -> 0
... B42: ='Property Management Overview'!B42 -> OTHER | C42: 0 | D42: 0 | E42: 0 | F42: 0 | G42: 0 | H42: 0 | I42: 0 | J42: 0 | K42: 0 | L42: 0 | M42: 0 | N42: 0 | O42: =SUM(C42:N42) -> 0
B43: TOTAL EXPENSES | C43: =SUM(C11:C42) -> 0 | D43: =SUM(D11:D42) -> 0 | E43: =SUM(E11:E42) -> 0 | F43: =SUM(F11:F42) -> 0 | G43: =SUM(G11:G42) -> 0 | H43: =SUM(H11:H42) -> 0 | I43: =SUM(I11:I42) -> 0 | J43: =SUM(J11:J42) -> 0 | ... N43: =SUM(N11:N42) -> 0 | O43: =SUM(C43:N43) -> 0
B45: YEAR-TO-DATE INCOME LESS EXPENSES | C45: =C7-C43 -> 0 | D45: =D7-D43 -> 0 | E45: =E7-E43 -> 0 | F45: =F7-F43 -> 0 | G45: =G7-G43 -> 0 | H45: =H7-H43 -> 0 | I45: =I7-I43 -> 0 | J45: =J7-J43 -> 0 | ... O45: =O7-O43 -> 0

Sheet Property 10
B1: PROPERTY MANAGEMENT SPREADSHEET TEMPLATE
B2: PROPERTY 10 ADDRESS | C2: 123 Main Street, City, State 10001
B3: INCOME | C3: JAN | D3: FEB | E3: MAR | F3: APR | G3: MAY | H3: JUN | I3: JUL | J3: AUG | K3: SEPT | L3: OCT | M3: NOV | N3: DEC | O3: YR TOTAL
B4: MULTI-PROPERTY INCOME OVERVIEW
B5: ='Property Management Overview'!B5 -> RENTAL INCOME | C5: 0 | D5: 0 | E5: 0 | F5: 0 | G5: 0 | H5: 0 | I5: 0 | J5: 0 | K5: 0 | L5: 0 | M5: 0 | N5: 0 | O5: =SUM(C5:N5) -> 0
B6: ='Property Management Overview'!B6 -> OTHER RENTAL INCOME – Late Fees, Etc. | C6: 0 | D6: 0 | E6: 0 | F6: 0 | G6: 0 | H6: 0 | I6: 0 | J6: 0 | K6: 0 | L6: 0 | M6: 0 | N6: 0 | O6: =SUM(C6:N6) -> 0
B7: GROSS RENTAL INCOME | C7: =SUM(C5:C6) -> 0 | D7: =SUM(D5:D6) -> 0 | E7: =SUM(E5:E6) -> 0 | F7: =SUM(F5:F6) -> 0 | G7: =SUM(G5:G6) -> 0 | H7: =SUM(H5:H6) -> 0 | I7: =SUM(I5:I6) -> 0 | J7: =SUM(J5:J6) -> 0 | ... N7: =SUM(N5:N6) -> 0 | O7: =SUM(C7:N7) -> 0
B9: EXPENSES | C9: JAN | D9: FEB | E9: MAR | F9: APR | G9: MAY | H9: JUN | I9: JUL | J9: AUG | K9: SEPT | L9: OCT | M9: NOV | N9: DEC | O9: YR TOTAL
B10: ='Property Management Overview'!B10 -> MULTI-PROPERTY EXPENSES OVERVIEW
B11: ='Property Management Overview'!B11 -> MARKETING / ADVERTISING | C11: 0 | D11: 0 | E11: 0 | F11: 0 | G11: 0 | H11: 0 | I11: 0 | J11: 0 | K11: 0 | L11: 0 | M11: 0 | N11: 0 | O11: =SUM(C11:N11) -> 0
B12: ='Property Management Overview'!B12 -> SERVICE CHARGE | C12: 0 | D12: 0 | E12: 0 | F12: 0 | G12: 0 | H12: 0 | I12: 0 | J12: 0 | K12: 0 | L12: 0 | M12: 0 | N12: 0 | O12: =SUM(C12:N12) -> 0
B13: ='Property Management Overview'!B13 -> AGENT FEES / COMMISSIONS | C13: 0 | D13: 0 | E13: 0 | F13: 0 | G13: 0 | H13: 0 | I13: 0 | J13: 0 | K13: 0 | L13: 0 | M13: 0 | N13: 0 | O13: =SUM(C13:N13) -> 0
B14: ='Property Management Overview'!B23 -> INSURANCE | C14: 0 | D14: 0 | E14: 0 | F14: 0 | G14: 0 | H14: 0 | I14: 0 | J14: 0 | K14: 0 | L14: 0 | M14: 0 | N14: 0 | O14: =SUM(C14:N14) -> 0
B15: ='Property Management Overview'!B15 -> INTERIOR MAINTENANCE | C15: 0 | D15: 0 | E15: 0 | F15: 0 | G15: 0 | H15: 0 | I15: 0 | J15: 0 | K15: 0 | L15: 0 | M15: 0 | N15: 0 | O15: =SUM(C15:N15) -> 0
B16: ='Property Management Overview'!B16 -> INTERIOR REPAIRS | C16: 0 | D16: 0 | E16: 0 | F16: 0 | G16: 0 | H16: 0 | I16: 0 | J16: 0 | K16: 0 | L16: 0 | M16: 0 | N16: 0 | O16: =SUM(C16:N16) -> 0
B17: ='Property Management Overview'!B17 -> HOUSEKEEPING | C17: 0 | D17: 0 | E17: 0 | F17: 0 | G17: 0 | H17: 0 | I17: 0 | J17: 0 | K17: 0 | L17: 0 | M17: 0 | N17: 0 | O17: =SUM(C17:N17) -> 0
B18: ='Property Management Overview'!B18 -> EXTERIOR MAINTENANCE | C18: 0 | D18: 0 | E18: 0 | F18: 0 | G18: 0 | H18: 0 | I18: 0 | J18: 0 | K18: 0 | L18: 0 | M18: 0 | N18: 0 | O18: =SUM(C18:N18) -> 0
B19: ='Property Management Overview'!B19 -> EXTERIOR REPAIRS | C19: 0 | D19: 0 | E19: 0 | F19: 0 | G19: 0 | H19: 0 | I19: 0 | J19: 0 | K19: 0 | L19: 0 | M19: 0 | N19: 0 | O19: =SUM(C19:N19) -> 0
B20: ='Property Management Overview'!B20 -> GROUNDSKEEPING | C20: 0 | D20: 0 | E20: 0 | F20: 0 | G20: 0 | H20: 0 | I20: 0 | J20: 0 | K20: 0 | L20: 0 | M20: 0 | N20: 0 | O20: =SUM(C20:N20) -> 0
B21: ='Property Management Overview'!B14 -> AIR+LISTRIK | C21: 0 | D21: 0 | E21: 0 | F21: 0 | G21: 0 | H21: 0 | I21: 0 | J21: 0 | K21: 0 | L21: 0 | M21: 0 | N21: 0 | O21: =SUM(C21:N21) -> 0
B22: ='Property Management Overview'!B22 -> GAS | C22: 0 | D22: 0 | E22: 0 | F22: 0 | G22: 0 | H22: 0 | I22: 0 | J22: 0 | K22: 0 | L22: 0 | M22: 0 | N22: 0 | O22: =SUM(C22:N22) -> 0
B23: =#REF! -> #REF! | C23: 0 | D23: 0 | E23: 0 | F23: 0 | G23: 0 | H23: 0 | I23: 0 | J23: 0 | K23: 0 | L23: 0 | M23: 0 | N23: 0 | O23: =SUM(C23:N23) -> 0
B24: ='Property Management Overview'!B24 -> SEWAGE | C24: 0 | D24: 0 | E24: 0 | F24: 0 | G24: 0 | H24: 0 | I24: 0 | J24: 0 | K24: 0 | L24: 0 | M24: 0 | N24: 0 | O24: =SUM(C24:N24) -> 0
B25: ='Property Management Overview'!B25 -> REFUSE | C25: 0 | D25: 0 | E25: 0 | F25: 0 | G25: 0 | H25: 0 | I25: 0 | J25: 0 | K25: 0 | L25: 0 | M25: 0 | N25: 0 | O25: =SUM(C25:N25) -> 0
B26: ='Property Management Overview'!B26 -> CORRESPONDENCE - Postage, Stationery, Phone, Etc. | C26: 0 | D26: 0 | E26: 0 | F26: 0 | G26: 0 | H26: 0 | I26: 0 | J26: 0 | K26: 0 | L26: 0 | M26: 0 | N26: 0 | O26: =SUM(C26:N26) -> 0
B27: ='Property Management Overview'!B27 -> CARETAKER FEES / SALARY | C27: 0 | D27: 0 | E27: 0 | F27: 0 | G27: 0 | H27: 0 | I27: 0 | J27: 0 | K27: 0 | L27: 0 | M27: 0 | N27: 0 | O27: =SUM(C27:N27) -> 0
B28: ='Property Management Overview'!B28 -> TRAVEL EXPENSES | C28: 0 | D28: 0 | E28: 0 | F28: 0 | G28: 0 | H28: 0 | I28: 0 | J28: 0 | K28: 0 | L28: 0 | M28: 0 | N28: 0 | O28: =SUM(C28:N28) -> 0
B29: ='Property Management Overview'!B29 -> EQUIPMENT / APPLIANCE PURCHASES | C29: 0 | D29: 0 | E29: 0 | F29: 0 | G29: 0 | H29: 0 | I29: 0 | J29: 0 | K29: 0 | L29: 0 | M29: 0 | N29: 0 | O29: =SUM(C29:N29) -> 0
B30: ='Property Management Overview'!B30 -> EQUIPMENT / APPLIANCE RENTAL FEES | C30: 0 | D30: 0 | E30: 0 | F30: 0 | G30: 0 | H30: 0 | I30: 0 | J30: 0 | K30: 0 | L30: 0 | M30: 0 | N30: 0 | O30: =SUM(C30:N30) -> 0
B31: ='Property Management Overview'!B31 -> LAND TAX | C31: 0 | D31: 0 | E31: 0 | F31: 0 | G31: 0 | H31: 0 | I31: 0 | J31: 0 | K31: 0 | L31: 0 | M31: 0 | N31: 0 | O31: =SUM(C31:N31) -> 0
B32: ='Property Management Overview'!B32 -> BORROWING EXPENSES | C32: 0 | D32: 0 | E32: 0 | F32: 0 | G32: 0 | H32: 0 | I32: 0 | J32: 0 | K32: 0 | L32: 0 | M32: 0 | N32: 0 | O32: =SUM(C32:N32) -> 0
B33: ='Property Management Overview'!B33 -> LOAN(S) INTEREST | C33: 0 | D33: 0 | E33: 0 | F33: 0 | G33: 0 | H33: 0 | I33: 0 | J33: 0 | K33: 0 | L33: 0 | M33: 0 | N33: 0 | O33: =SUM(C33:N33) -> 0
B34: ='Property Management Overview'!B34 -> TRAVEL EXPENSES | C34: 0 | D34: 0 | E34: 0 | F34: 0 | G34: 0 | H34: 0 | I34: 0 | J34: 0 | K34: 0 | L34: 0 | M34: 0 | N34: 0 | O34: =SUM(C34:N34) -> 0
B35: ='Property Management Overview'!B35 -> OTHER | C35: 0 | D35: 0 | E35: 0 | F35: 0 | G35: 0 | H35: 0 | I35: 0 | J35: 0 | K35: 0 | L35: 0 | M35: 0 | N35: 0 | O35: =SUM(C35:N35) -> 0
... B42: ='Property Management Overview'!B42 -> OTHER | C42: 0 | D42: 0 | E42: 0 | F42: 0 | G42: 0 | H42: 0 | I42: 0 | J42: 0 | K42: 0 | L42: 0 | M42: 0 | N42: 0 | O42: =SUM(C42:N42) -> 0
B43: TOTAL EXPENSES | C43: =SUM(C11:C42) -> 0 | D43: =SUM(D11:D42) -> 0 | E43: =SUM(E11:E42) -> 0 | F43: =SUM(F11:F42) -> 0 | G43: =SUM(G11:G42) -> 0 | H43: =SUM(H11:H42) -> 0 | I43: =SUM(I11:I42) -> 0 | J43: =SUM(J11:J42) -> 0 | ... N43: =SUM(N11:N42) -> 0 | O43: =SUM(C43:N43) -> 0
B45: YEAR-TO-DATE INCOME LESS EXPENSES | C45: =C7-C43 -> 0 | D45: =D7-D43 -> 0 | E45: =E7-E43 -> 0 | F45: =F7-F43 -> 0 | G45: =G7-G43 -> 0 | H45: =H7-H43 -> 0 | I45: =I7-I43 -> 0 | J45: =J7-J43 -> 0 | ... O45: =O7-O43 -> 0

Sheet Property 11
B1: PROPERTY MANAGEMENT SPREADSHEET TEMPLATE
B2: PROPERTY 11 ADDRESS | C2: 123 Main Street, City, State 10001
B3: INCOME | C3: JAN | D3: FEB | E3: MAR | F3: APR | G3: MAY | H3: JUN | I3: JUL | J3: AUG | K3: SEPT | L3: OCT | M3: NOV | N3: DEC | O3: YR TOTAL
B4: MULTI-PROPERTY INCOME OVERVIEW
B5: ='Property Management Overview'!B5 -> RENTAL INCOME | C5: 0 | D5: 0 | E5: 0 | F5: 0 | G5: 0 | H5: 0 | I5: 0 | J5: 0 | K5: 0 | L5: 0 | M5: 0 | N5: 0 | O5: =SUM(C5:N5) -> 0
B6: ='Property Management Overview'!B6 -> OTHER RENTAL INCOME – Late Fees, Etc. | C6: 0 | D6: 0 | E6: 0 | F6: 0 | G6: 0 | H6: 0 | I6: 0 | J6: 0 | K6: 0 | L6: 0 | M6: 0 | N6: 0 | O6: =SUM(C6:N6) -> 0
B7: GROSS RENTAL INCOME | C7: =SUM(C5:C6) -> 0 | D7: =SUM(D5:D6) -> 0 | E7: =SUM(E5:E6) -> 0 | F7: =SUM(F5:F6) -> 0 | G7: =SUM(G5:G6) -> 0 | H7: =SUM(H5:H6) -> 0 | I7: =SUM(I5:I6) -> 0 | J7: =SUM(J5:J6) -> 0 | ... N7: =SUM(N5:N6) -> 0 | O7: =SUM(C7:N7) -> 0
B9: EXPENSES | C9: JAN | D9: FEB | E9: MAR | F9: APR | G9: MAY | H9: JUN | I9: JUL | J9: AUG | K9: SEPT | L9: OCT | M9: NOV | N9: DEC | O9: YR TOTAL
B10: ='Property Management Overview'!B10 -> MULTI-PROPERTY EXPENSES OVERVIEW
B11: ='Property Management Overview'!B11 -> MARKETING / ADVERTISING | C11: 0 | D11: 0 | E11: 0 | F11: 0 | G11: 0 | H11: 0 | I11: 0 | J11: 0 | K11: 0 | L11: 0 | M11: 0 | N11: 0 | O11: =SUM(C11:N11) -> 0
B12: ='Property Management Overview'!B12 -> SERVICE CHARGE | C12: 0 | D12: 0 | E12: 0 | F12: 0 | G12: 0 | H12: 0 | I12: 0 | J12: 0 | K12: 0 | L12: 0 | M12: 0 | N12: 0 | O12: =SUM(C12:N12) -> 0
B13: ='Property Management Overview'!B13 -> AGENT FEES / COMMISSIONS | C13: 0 | D13: 0 | E13: 0 | F13: 0 | G13: 0 | H13: 0 | I13: 0 | J13: 0 | K13: 0 | L13: 0 | M13: 0 | N13: 0 | O13: =SUM(C13:N13) -> 0
B14: ='Property Management Overview'!B23 -> INSURANCE | C14: 0 | D14: 0 | E14: 0 | F14: 0 | G14: 0 | H14: 0 | I14: 0 | J14: 0 | K14: 0 | L14: 0 | M14: 0 | N14: 0 | O14: =SUM(C14:N14) -> 0
B15: ='Property Management Overview'!B15 -> INTERIOR MAINTENANCE | C15: 0 | D15: 0 | E15: 0 | F15: 0 | G15: 0 | H15: 0 | I15: 0 | J15: 0 | K15: 0 | L15: 0 | M15: 0 | N15: 0 | O15: =SUM(C15:N15) -> 0
B16: ='Property Management Overview'!B16 -> INTERIOR REPAIRS | C16: 0 | D16: 0 | E16: 0 | F16: 0 | G16: 0 | H16: 0 | I16: 0 | J16: 0 | K16: 0 | L16: 0 | M16: 0 | N16: 0 | O16: =SUM(C16:N16) -> 0
B17: ='Property Management Overview'!B17 -> HOUSEKEEPING | C17: 0 | D17: 0 | E17: 0 | F17: 0 | G17: 0 | H17: 0 | I17: 0 | J17: 0 | K17: 0 | L17: 0 | M17: 0 | N17: 0 | O17: =SUM(C17:N17) -> 0
B18: ='Property Management Overview'!B18 -> EXTERIOR MAINTENANCE | C18: 0 | D18: 0 | E18: 0 | F18: 0 | G18: 0 | H18: 0 | I18: 0 | J18: 0 | K18: 0 | L18: 0 | M18: 0 | N18: 0 | O18: =SUM(C18:N18) -> 0
B19: ='Property Management Overview'!B19 -> EXTERIOR REPAIRS | C19: 0 | D19: 0 | E19: 0 | F19: 0 | G19: 0 | H19: 0 | I19: 0 | J19: 0 | K19: 0 | L19: 0 | M19: 0 | N19: 0 | O19: =SUM(C19:N19) -> 0
B20: ='Property Management Overview'!B20 -> GROUNDSKEEPING | C20: 0 | D20: 0 | E20: 0 | F20: 0 | G20: 0 | H20: 0 | I20: 0 | J20: 0 | K20: 0 | L20: 0 | M20: 0 | N20: 0 | O20: =SUM(C20:N20) -> 0
B21: ='Property Management Overview'!B14 -> AIR+LISTRIK | C21: 0 | D21: 0 | E21: 0 | F21: 0 | G21: 0 | H21: 0 | I21: 0 | J21: 0 | K21: 0 | L21: 0 | M21: 0 | N21: 0 | O21: =SUM(C21:N21) -> 0
B22: ='Property Management Overview'!B22 -> GAS | C22: 0 | D22: 0 | E22: 0 | F22: 0 | G22: 0 | H22: 0 | I22: 0 | J22: 0 | K22: 0 | L22: 0 | M22: 0 | N22: 0 | O22: =SUM(C22:N22) -> 0
B23: =#REF! -> #REF! | C23: 0 | D23: 0 | E23: 0 | F23: 0 | G23: 0 | H23: 0 | I23: 0 | J23: 0 | K23: 0 | L23: 0 | M23: 0 | N23: 0 | O23: =SUM(C23:N23) -> 0
B24: ='Property Management Overview'!B24 -> SEWAGE | C24: 0 | D24: 0 | E24: 0 | F24: 0 | G24: 0 | H24: 0 | I24: 0 | J24: 0 | K24: 0 | L24: 0 | M24: 0 | N24: 0 | O24: =SUM(C24:N24) -> 0
B25: ='Property Management Overview'!B25 -> REFUSE | C25: 0 | D25: 0 | E25: 0 | F25: 0 | G25: 0 | H25: 0 | I25: 0 | J25: 0 | K25: 0 | L25: 0 | M25: 0 | N25: 0 | O25: =SUM(C25:N25) -> 0
B26: ='Property Management Overview'!B26 -> CORRESPONDENCE - Postage, Stationery, Phone, Etc. | C26: 0 | D26: 0 | E26: 0 | F26: 0 | G26: 0 | H26: 0 | I26: 0 | J26: 0 | K26: 0 | L26: 0 | M26: 0 | N26: 0 | O26: =SUM(C26:N26) -> 0
B27: ='Property Management Overview'!B27 -> CARETAKER FEES / SALARY | C27: 0 | D27: 0 | E27: 0 | F27: 0 | G27: 0 | H27: 0 | I27: 0 | J27: 0 | K27: 0 | L27: 0 | M27: 0 | N27: 0 | O27: =SUM(C27:N27) -> 0
B28: ='Property Management Overview'!B28 -> TRAVEL EXPENSES | C28: 0 | D28: 0 | E28: 0 | F28: 0 | G28: 0 | H28: 0 | I28: 0 | J28: 0 | K28: 0 | L28: 0 | M28: 0 | N28: 0 | O28: =SUM(C28:N28) -> 0
B29: ='Property Management Overview'!B29 -> EQUIPMENT / APPLIANCE PURCHASES | C29: 0 | D29: 0 | E29: 0 | F29: 0 | G29: 0 | H29: 0 | I29: 0 | J29: 0 | K29: 0 | L29: 0 | M29: 0 | N29: 0 | O29: =SUM(C29:N29) -> 0
B30: ='Property Management Overview'!B30 -> EQUIPMENT / APPLIANCE RENTAL FEES | C30: 0 | D30: 0 | E30: 0 | F30: 0 | G30: 0 | H30: 0 | I30: 0 | J30: 0 | K30: 0 | L30: 0 | M30: 0 | N30: 0 | O30: =SUM(C30:N30) -> 0
B31: ='Property Management Overview'!B31 -> LAND TAX | C31: 0 | D31: 0 | E31: 0 | F31: 0 | G31: 0 | H31: 0 | I31: 0 | J31: 0 | K31: 0 | L31: 0 | M31: 0 | N31: 0 | O31: =SUM(C31:N31) -> 0
B32: ='Property Management Overview'!B32 -> BORROWING EXPENSES | C32: 0 | D32: 0 | E32: 0 | F32: 0 | G32: 0 | H32: 0 | I32: 0 | J32: 0 | K32: 0 | L32: 0 | M32: 0 | N32: 0 | O32: =SUM(C32:N32) -> 0
B33: ='Property Management Overview'!B33 -> LOAN(S) INTEREST | C33: 0 | D33: 0 | E33: 0 | F33: 0 | G33: 0 | H33: 0 | I33: 0 | J33: 0 | K33: 0 | L33: 0 | M33: 0 | N33: 0 | O33: =SUM(C33:N33) -> 0
B34: ='Property Management Overview'!B34 -> TRAVEL EXPENSES | C34: 0 | D34: 0 | E34: 0 | F34: 0 | G34: 0 | H34: 0 | I34: 0 | J34: 0 | K34: 0 | L34: 0 | M34: 0 | N34: 0 | O34: =SUM(C34:N34) -> 0
B35: ='Property Management Overview'!B35 -> OTHER | C35: 0 | D35: 0 | E35: 0 | F35: 0 | G35: 0 | H35: 0 | I35: 0 | J35: 0 | K35: 0 | L35: 0 | M35: 0 | N35: 0 | O35: =SUM(C35:N35) -> 0
... B42: ='Property Management Overview'!B42 -> OTHER | C42: 0 | D42: 0 | E42: 0 | F42: 0 | G42: 0 | H42: 0 | I42: 0 | J42: 0 | K42: 0 | L42: 0 | M42: 0 | N42: 0 | O42: =SUM(C42:N42) -> 0
B43: TOTAL EXPENSES | C43: =SUM(C11:C42) -> 0 | D43: =SUM(D11:D42) -> 0 | E43: =SUM(E11:E42) -> 0 | F43: =SUM(F11:F42) -> 0 | G43: =SUM(G11:G42) -> 0 | H43: =SUM(H11:H42) -> 0 | I43: =SUM(I11:I42) -> 0 | J43: =SUM(J11:J42) -> 0 | ... N43: =SUM(N11:N42) -> 0 | O43: =SUM(C43:N43) -> 0
B45: YEAR-TO-DATE INCOME LESS EXPENSES | C45: =C7-C43 -> 0 | D45: =D7-D43 -> 0 | E45: =E7-E43 -> 0 | F45: =F7-F43 -> 0 | G45: =G7-G43 -> 0 | H45: =H7-H43 -> 0 | I45: =I7-I43 -> 0 | J45: =J7-J43 -> 0 | ... O45: =O7-O43 -> 0

Sheet Property 12
B1: PROPERTY MANAGEMENT SPREADSHEET TEMPLATE
B2: PROPERTY 12 ADDRESS | C2: 123 Main Street, City, State 10001
B3: INCOME | C3: JAN | D3: FEB | E3: MAR | F3: APR | G3: MAY | H3: JUN | I3: JUL | J3: AUG | K3: SEPT | L3: OCT | M3: NOV | N3: DEC | O3: YR TOTAL
B4: MULTI-PROPERTY INCOME OVERVIEW
B5: ='Property Management Overview'!B5 -> RENTAL INCOME | C5: 0 | D5: 0 | E5: 0 | F5: 0 | G5: 0 | H5: 0 | I5: 0 | J5: 0 | K5: 0 | L5: 0 | M5: 0 | N5: 0 | O5: =SUM(C5:N5) -> 0
B6: ='Property Management Overview'!B6 -> OTHER RENTAL INCOME – Late Fees, Etc. | C6: 0 | D6: 0 | E6: 0 | F6: 0 | G6: 0 | H6: 0 | I6: 0 | J6: 0 | K6: 0 | L6: 0 | M6: 0 | N6: 0 | O6: =SUM(C6:N6) -> 0
B7: GROSS RENTAL INCOME | C7: =SUM(C5:C6) -> 0 | D7: =SUM(D5:D6) -> 0 | E7: =SUM(E5:E6) -> 0 | F7: =SUM(F5:F6) -> 0 | G7: =SUM(G5:G6) -> 0 | H7: =SUM(H5:H6) -> 0 | I7: =SUM(I5:I6) -> 0 | J7: =SUM(J5:J6) -> 0 | ... N7: =SUM(N5:N6) -> 0 | O7: =SUM(C7:N7) -> 0
B9: EXPENSES | C9: JAN | D9: FEB | E9: MAR | F9: APR | G9: MAY | H9: JUN | I9: JUL | J9: AUG | K9: SEPT | L9: OCT | M9: NOV | N9: DEC | O9: YR TOTAL
B10: ='Property Management Overview'!B10 -> MULTI-PROPERTY EXPENSES OVERVIEW
B11: ='Property Management Overview'!B11 -> MARKETING / ADVERTISING | C11: 0 | D11: 0 | E11: 0 | F11: 0 | G11: 0 | H11: 0 | I11: 0 | J11: 0 | K11: 0 | L11: 0 | M11: 0 | N11: 0 | O11: =SUM(C11:N11) -> 0
B12: ='Property Management Overview'!B12 -> SERVICE CHARGE | C12: 0 | D12: 0 | E12: 0 | F12: 0 | G12: 0 | H12: 0 | I12: 0 | J12: 0 | K12: 0 | L12: 0 | M12: 0 | N12: 0 | O12: =SUM(C12:N12) -> 0
B13: ='Property Management Overview'!B13 -> AGENT FEES / COMMISSIONS | C13: 0 | D13: 0 | E13: 0 | F13: 0 | G13: 0 | H13: 0 | I13: 0 | J13: 0 | K13: 0 | L13: 0 | M13: 0 | N13: 0 | O13: =SUM(C13:N13) -> 0
B14: ='Property Management Overview'!B23 -> INSURANCE | C14: 0 | D14: 0 | E14: 0 | F14: 0 | G14: 0 | H14: 0 | I14: 0 | J14: 0 | K14: 0 | L14: 0 | M14: 0 | N14: 0 | O14: =SUM(C14:N14) -> 0
B15: ='Property Management Overview'!B15 -> INTERIOR MAINTENANCE | C15: 0 | D15: 0 | E15: 0 | F15: 0 | G15: 0 | H15: 0 | I15: 0 | J15: 0 | K15: 0 | L15: 0 | M15: 0 | N15: 0 | O15: =SUM(C15:N15) -> 0
B16: ='Property Management Overview'!B16 -> INTERIOR REPAIRS | C16: 0 | D16: 0 | E16: 0 | F16: 0 | G16: 0 | H16: 0 | I16: 0 | J16: 0 | K16: 0 | L16: 0 | M16: 0 | N16: 0 | O16: =SUM(C16:N16) -> 0
B17: ='Property Management Overview'!B17 -> HOUSEKEEPING | C17: 0 | D17: 0 | E17: 0 | F17: 0 | G17: 0 | H17: 0 | I17: 0 | J17: 0 | K17: 0 | L17: 0 | M17: 0 | N17: 0 | O17: =SUM(C17:N17) -> 0
B18: ='Property Management Overview'!B18 -> EXTERIOR MAINTENANCE | C18: 0 | D18: 0 | E18: 0 | F18: 0 | G18: 0 | H18: 0 | I18: 0 | J18: 0 | K18: 0 | L18: 0 | M18: 0 | N18: 0 | O18: =SUM(C18:N18) -> 0
B19: ='Property Management Overview'!B19 -> EXTERIOR REPAIRS | C19: 0 | D19: 0 | E19: 0 | F19: 0 | G19: 0 | H19: 0 | I19: 0 | J19: 0 | K19: 0 | L19: 0 | M19: 0 | N19: 0 | O19: =SUM(C19:N19) -> 0
B20: ='Property Management Overview'!B20 -> GROUNDSKEEPING | C20: 0 | D20: 0 | E20: 0 | F20: 0 | G20: 0 | H20: 0 | I20: 0 | J20: 0 | K20: 0 | L20: 0 | M20: 0 | N20: 0 | O20: =SUM(C20:N20) -> 0
B21: ='Property Management Overview'!B14 -> AIR+LISTRIK | C21: 0 | D21: 0 | E21: 0 | F21: 0 | G21: 0 | H21: 0 | I21: 0 | J21: 0 | K21: 0 | L21: 0 | M21: 0 | N21: 0 | O21: =SUM(C21:N21) -> 0
B22: ='Property Management Overview'!B22 -> GAS | C22: 0 | D22: 0 | E22: 0 | F22: 0 | G22: 0 | H22: 0 | I22: 0 | J22: 0 | K22: 0 | L22: 0 | M22: 0 | N22: 0 | O22: =SUM(C22:N22) -> 0
B23: =#REF! -> #REF! | C23: 0 | D23: 0 | E23: 0 | F23: 0 | G23: 0 | H23: 0 | I23: 0 | J23: 0 | K23: 0 | L23: 0 | M23: 0 | N23: 0 | O23: =SUM(C23:N23) -> 0
B24: ='Property Management Overview'!B24 -> SEWAGE | C24: 0 | D24: 0 | E24: 0 | F24: 0 | G24: 0 | H24: 0 | I24: 0 | J24: 0 | K24: 0 | L24: 0 | M24: 0 | N24: 0 | O24: =SUM(C24:N24) -> 0
B25: ='Property Management Overview'!B25 -> REFUSE | C25: 0 | D25: 0 | E25: 0 | F25: 0 | G25: 0 | H25: 0 | I25: 0 | J25: 0 | K25: 0 | L25: 0 | M25: 0 | N25: 0 | O25: =SUM(C25:N25) -> 0
B26: ='Property Management Overview'!B26 -> CORRESPONDENCE - Postage, Stationery, Phone, Etc. | C26: 0 | D26: 0 | E26: 0 | F26: 0 | G26: 0 | H26: 0 | I26: 0 | J26: 0 | K26: 0 | L26: 0 | M26: 0 | N26: 0 | O26: =SUM(C26:N26) -> 0
B27: ='Property Management Overview'!B27 -> CARETAKER FEES / SALARY | C27: 0 | D27: 0 | E27: 0 | F27: 0 | G27: 0 | H27: 0 | I27: 0 | J27: 0 | K27: 0 | L27: 0 | M27: 0 | N27: 0 | O27: =SUM(C27:N27) -> 0
B28: ='Property Management Overview'!B28 -> TRAVEL EXPENSES | C28: 0 | D28: 0 | E28: 0 | F28: 0 | G28: 0 | H28: 0 | I28: 0 | J28: 0 | K28: 0 | L28: 0 | M28: 0 | N28: 0 | O28: =SUM(C28:N28) -> 0
B29: ='Property Management Overview'!B29 -> EQUIPMENT / APPLIANCE PURCHASES | C29: 0 | D29: 0 | E29: 0 | F29: 0 | G29: 0 | H29: 0 | I29: 0 | J29: 0 | K29: 0 | L29: 0 | M29: 0 | N29: 0 | O29: =SUM(C29:N29) -> 0
B30: ='Property Management Overview'!B30 -> EQUIPMENT / APPLIANCE RENTAL FEES | C30: 0 | D30: 0 | E30: 0 | F30: 0 | G30: 0 | H30: 0 | I30: 0 | J30: 0 | K30: 0 | L30: 0 | M30: 0 | N30: 0 | O30: =SUM(C30:N30) -> 0
B31: ='Property Management Overview'!B31 -> LAND TAX | C31: 0 | D31: 0 | E31: 0 | F31: 0 | G31: 0 | H31: 0 | I31: 0 | J31: 0 | K31: 0 | L31: 0 | M31: 0 | N31: 0 | O31: =SUM(C31:N31) -> 0
B32: ='Property Management Overview'!B32 -> BORROWING EXPENSES | C32: 0 | D32: 0 | E32: 0 | F32: 0 | G32: 0 | H32: 0 | I32: 0 | J32: 0 | K32: 0 | L32: 0 | M32: 0 | N32: 0 | O32: =SUM(C32:N32) -> 0
B33: ='Property Management Overview'!B33 -> LOAN(S) INTEREST | C33: 0 | D33: 0 | E33: 0 | F33: 0 | G33: 0 | H33: 0 | I33: 0 | J33: 0 | K33: 0 | L33: 0 | M33: 0 | N33: 0 | O33: =SUM(C33:N33) -> 0
B34: ='Property Management Overview'!B34 -> TRAVEL EXPENSES | C34: 0 | D34: 0 | E34: 0 | F34: 0 | G34: 0 | H34: 0 | I34: 0 | J34: 0 | K34: 0 | L34: 0 | M34: 0 | N34: 0 | O34: =SUM(C34:N34) -> 0
B35: ='Property Management Overview'!B35 -> OTHER | C35: 0 | D35: 0 | E35: 0 | F35: 0 | G35: 0 | H35: 0 | I35: 0 | J35: 0 | K35: 0 | L35: 0 | M35: 0 | N35: 0 | O35: =SUM(C35:N35) -> 0
... B42: ='Property Management Overview'!B42 -> OTHER | C42: 0 | D42: 0 | E42: 0 | F42: 0 | G42: 0 | H42: 0 | I42: 0 | J42: 0 | K42: 0 | L42: 0 | M42: 0 | N42: 0 | O42: =SUM(C42:N42) -> 0
B43: TOTAL EXPENSES | C43: =SUM(C11:C42) -> 0 | D43: =SUM(D11:D42) -> 0 | E43: =SUM(E11:E42) -> 0 | F43: =SUM(F11:F42) -> 0 | G43: =SUM(G11:G42) -> 0 | H43: =SUM(H11:H42) -> 0 | I43: =SUM(I11:I42) -> 0 | J43: =SUM(J11:J42) -> 0 | ... N43: =SUM(N11:N42) -> 0 | O43: =SUM(C43:N43) -> 0
B45: YEAR-TO-DATE INCOME LESS EXPENSES | C45: =C7-C43 -> 0 | D45: =D7-D43 -> 0 | E45: =E7-E43 -> 0 | F45: =F7-F43 -> 0 | G45: =G7-G43 -> 0 | H45: =H7-H43 -> 0 | I45: =I7-I43 -> 0 | J45: =J7-J43 -> 0 | ... O45: =O7-O43 -> 0

Sheet - Disclaimer -
B2: Any articles, templates, or information provided by Smartsheet on the website are for reference only. While we strive to keep the information up to date and correct, we make no representations or warranties of any kind, express or implied, about the completeness, accuracy, reliability, suitability, or availability with respect to the website or the information, articles, templates, or related graphics contained on the website. Any reliance you place on such information is therefore strictly at your own risk.
